Workbook

Sheet Hướng dẫn
A1: DATA DICTIONARY — POC Doanh thu bảo hiểm — dữ liệu khối lượng lớn (PostgreSQL)
A2: Sinh tự động từ catalog PostgreSQL reportapi — bronze.ins_* (scripts/build_docs.py, DOCS_TARGET=volume) ngày 19/10/2026. Tên bảng ghi theo mô hình logic: ref.X / core.X = bronze.ins_X.
A4: Mục | B4: Nội dung
A5: Mục đích | B5: Mô tả chi tiết các bảng/cột của DỮ LIỆU NGUỒN được sinh ra cho POC doanh thu bảo hiểm (đủ thông tin cho 6 chiều phân tích: Thời gian, Kênh bán, Nghiệp vụ, Sản phẩm, Đơn vị, Khách hàng).
A6: Lớp 'Danh mục' (schema ref) | B6: Danh mục chuẩn hóa theo nguồn public: Luật KDBH 2022, NĐ 46/2023, NĐ 67/2023, TT 67/2023, TT 232/2012, NQ 202/2025, số liệu IAV/MOF.
A7: Lớp 'Giao dịch' (schema core) | B7: Hợp đồng → giao dịch → chi tiết phí theo sản phẩm; đồng bảo hiểm; phân bổ doanh thu cho đơn vị.
A8: Cách tính doanh thu từ dữ liệu nguồn | B8: premium_vnd × share_pct('OWN')/100 × allocation_pct/100 (VND, chưa VAT); chỉ giao dịch APPROVED; kỳ theo accounting_date.
A9: Sheet 'Tổng quan bảng' | B9: 1 dòng / bảng. Bấm tên bảng để mở sheet chi tiết của bảng đó. 'Số cột' là công thức đếm từ sheet bảng.
A10: Sheet theo bảng (vd 'core.policy') | B10: Mỗi bảng 1 sheet, tên sheet = schema.bảng, màu tab theo lớp. Gồm: (1) thông tin bảng — lớp, mô tả, grain, khóa chính, số dòng, căn cứ; (2) danh sách cột — kiểu dữ liệu, NOT NULL/PK/FK/UNIQUE, mô tả, căn cứ, giá trị mẫu, số giá trị khác nhau, % NULL; (3) khóa ngoại đi ra và bảng tham chiếu tới; (4) 5 dòng dữ liệu mẫu.
A11: Sheet 'Quan hệ FK' | B11: Toàn bộ khóa ngoại: bảng/cột con → bảng/cột cha (bấm tên bảng để mở sheet).
A12: Sheet 'Quy tắc nghiệp vụ' | B12: Các quy tắc tính doanh thu và căn cứ pháp lý.
A13: Sheet 'Kịch bản dữ liệu' | B13: Các tình huống cài sẵn trong dữ liệu dummy để kiểm thử ETL.
A14: Sheet 'DM …' | B14: Giá trị các danh mục mã chính (sản phẩm, kênh/đối tác, loại giao dịch, đơn vị, dòng báo cáo).
A15: Màu | B15: Tab / cột 'Lớp': xanh dương = Danh mục · cam = Giao dịch · xanh lá = Phân tích. Tên cột khóa chính in đậm.
A16: Lưu ý dữ liệu | B16: Danh mục doanh nghiệp là Tổng Công ty Bảo hiểm PVI với 47 đơn vị thật (pvi.com.vn/vi/network); 3 đối tác số có công bố hợp tác với PVI mang tên thật (Green SM, ATADI, Fuse); các đối tác khác và DN đồng bảo hiểm ẩn danh. Mọi giao dịch, số tiền, khách hàng là giả lập — không phải số liệu thật của PVI hay của từng đơn vị.

Sheet Tổng quan bảng
A1: Tổng quan bảng
A2: Sinh tự động từ catalog PostgreSQL reportapi — bronze.ins_* (scripts/build_docs.py, DOCS_TARGET=volume) ngày 19/10/2026. Tên bảng ghi theo mô hình logic: ref.X / core.X = bronze.ins_X.
A4: STT | B4: Schema | C4: Bảng (bấm để mở) | D4: Lớp | E4: Mô tả | F4: Grain (1 dòng là gì) | G4: Khóa chính | H4: Số cột | I4: Số dòng (dummy) | J4: Căn cứ / chuẩn tham chiếu
A5: 1 | B5: ref | C5: region | D5: Danh mục | E5: Vùng miền dùng để nhóm tỉnh/thành | F5: 1 dòng / vùng | G5: region_code | H5: =COUNT('ref.region'!$A$15:$A$400) | I5: 3 | J5: Đề xuất của dự án (không có văn bản pháp lý chia 3 miền)
A6: 2 | B6: ref | C6: province | D6: Danh mục | E6: Tỉnh/thành phố theo đơn vị hành chính hiện hành (34 đơn vị) | F6: 1 dòng / tỉnh-thành | G6: province_code | H6: =COUNT('ref.province'!$A$15:$A$400) | I6: 34 | J6: NQ 202/2025/QH15
A7: 3 | B7: ref | C7: company | D7: Danh mục | E7: Cơ cấu tổ chức: Tổng công ty → khối trụ sở, công ty thành viên, đơn vị kinh doanh số | F7: 1 dòng / đơn vị | G7: company_code | H7: =COUNT('ref.company'!$A$15:$A$400) | I7: 49 | J7: Mô hình Tổng công ty – công ty thành viên công khai của các DNBH (BCTN Bảo Việt, PVI)
A8: 4 | B8: ref | C8: line_of_business | D8: Danh mục | E8: Nghiệp vụ bảo hiểm + nhóm phân tích POC (Xe / Con người / Tài sản) | F8: 1 dòng / nghiệp vụ | G8: lob_code | H8: =COUNT('ref.line_of_business'!$A$15:$A$400) | I8: 4 | J8: Luật KDBH 2022 Điều 7; NĐ 46/2023/NĐ-CP Điều 4–5
A9: 5 | B9: ref | C9: regulatory_line | D9: Danh mục | E9: Dòng báo cáo nghiệp vụ theo mẫu báo cáo Bộ Tài chính (cây cha–con) | F9: 1 dòng / dòng báo cáo | G9: report_line_code | H9: =COUNT('ref.regulatory_line'!$A$15:$A$400) | I9: 14 | J9: TT 67/2023/TT-BTC Phụ lục VI – Mẫu 1-PNT/2-PNT
A10: 6 | B10: ref | C10: product_group | D10: Danh mục | E10: Nhóm sản phẩm — cấp giữa Nghiệp vụ và Sản phẩm, đúng 8 nhóm của đề bài | F10: 1 dòng / nhóm SP | G10: product_group_code | H10: =COUNT('ref.product_group'!$A$15:$A$400) | I10: 8 | J10: Phạm vi đề bài POC
A11: 7 | B11: ref | C11: product | D11: Danh mục | E11: Sản phẩm bảo hiểm (phạm vi POC) | F11: 1 dòng / sản phẩm | G11: product_code | H11: =COUNT('ref.product'!$A$15:$A$400) | I11: 23 | J11: NĐ 67/2023/NĐ-CP; Luật GTGT 48/2024; TT 67/2023/TT-BTC Điều 51
A12: 8 | B12: ref | C12: channel | D12: Danh mục | E12: Kênh phân phối theo hình thức cung cấp sản phẩm bảo hiểm | F12: 1 dòng / kênh | G12: channel_code | H12: =COUNT('ref.channel'!$A$15:$A$400) | I12: 7 | J12: Luật KDBH 2022 Điều 87 khoản 4; TT 67/2023/TT-BTC Mẫu 3-PNT
A13: 9 | B13: ref | C13: partner | D13: Danh mục | E13: Đối tác phân phối — ngân hàng, đăng kiểm, OTA, ví điện tử... (ẩn danh); 3 đối tác số tên thật có công bố hợp tác với PVI: Green SM, ATADI, Fuse | F13: 1 dòng / đối tác | G13: partner_code | H13: =COUNT('ref.partner'!$A$15:$A$400) | I13: 39 | J13: Loại đối tác theo thực tế thị trường; đối tác truyền thống ẩn danh, đối tác bảo hiểm vi mô theo nguồn công khai (sources/market_data.md mục 10)
A14: 10 | B14: ref | C14: customer_segment | D14: Danh mục | E14: Phân khúc khách hàng | F14: 1 dòng / phân khúc | G14: segment_code | H14: =COUNT('ref.customer_segment'!$A$15:$A$400) | I14: 6 | J14: Phân loại phổ biến (cá nhân / hộ gia đình / doanh nghiệp / cơ quan NN / cơ sở giáo dục)
A15: 11 | B15: ref | C15: customer | D15: Danh mục | E15: Khách hàng — bên mua bảo hiểm (dữ liệu giả) | F15: 1 dòng / khách hàng | G15: customer_code | H15: =COUNT('ref.customer'!$A$15:$A$400) | I15: 1696375 | J15: Dữ liệu sinh ngẫu nhiên
A16: 12 | B16: ref | C16: currency | D16: Danh mục | E16: Tiền tệ | F16: 1 dòng / loại tiền | G16: currency_code | H16: =COUNT('ref.currency'!$A$15:$A$400) | I16: 2 | J16: ISO 4217
A17: 13 | B17: ref | C17: fx_rate | D17: Danh mục | E17: Tỷ giá hạch toán theo tháng | F17: 1 dòng / loại tiền × tháng | G17: currency_code, rate_month | H17: =COUNT('ref.fx_rate'!$A$15:$A$400) | I17: 60 | J17: Tỷ giá hạch toán KBNN 2025; 2024 ước tính
A18: 14 | B18: ref | C18: transaction_type | D18: Danh mục | E18: Loại giao dịch phí: cấp mới, tái tục, SĐBS, hoàn phí, hủy | F18: 1 dòng / loại giao dịch | G18: txn_type_code | H18: =COUNT('ref.transaction_type'!$A$15:$A$400) | I18: 7 | J18: NĐ 46/2023/NĐ-CP Điều 49; TT 232/2012/TT-BTC; ACORD BusinessPurposeTypeCd
A19: 15 | B19: ref | C19: insurer | D19: Danh mục | E19: Doanh nghiệp bảo hiểm tham gia đồng bảo hiểm (ẩn danh); OWN = chính công ty | F19: 1 dòng / DNBH | G19: insurer_code | H19: =COUNT('ref.insurer'!$A$15:$A$400) | I19: 7 | J19: Luật KDBH 2022 Điều 4 khoản 29
A20: 16 | B20: ref | C20: allocation_type | D20: Danh mục | E20: Loại phân bổ doanh thu giữa các đơn vị | F20: 1 dòng / loại | G20: allocation_type_code | H20: =COUNT('ref.allocation_type'!$A$15:$A$400) | I20: 3 | J20: Thông lệ quản trị nội bộ
A21: 17 | B21: core | C21: policy | D21: Giao dịch | E21: Hợp đồng / đơn bảo hiểm | F21: 1 dòng / hợp đồng | G21: policy_id | H21: =COUNT('core.policy'!$A$15:$A$400) | I21: 4082637 | J21: Luật KDBH 2022; ACORD Policy; IBM IIW Agreement
A22: 18 | B22: core | C22: policy_transaction | D22: Giao dịch | E22: Giao dịch phát sinh phí của hợp đồng (cấp mới, tái tục, SĐBS, hoàn phí, hủy) | F22: 1 dòng / giao dịch | G22: txn_id | H22: =COUNT('core.policy_transaction'!$A$15:$A$400) | I22: 4098401 | J22: NĐ 46/2023/NĐ-CP Điều 49; TT 232/2012/TT-BTC TK 5111/5311/5321; Microsoft CDM PolicyTransaction
A23: 19 | B23: core | C23: transaction_coverage | D23: Giao dịch | E23: Phí 100% hợp đồng theo từng sản phẩm của giao dịch | F23: 1 dòng / giao dịch × sản phẩm | G23: coverage_id | H23: =COUNT('core.transaction_coverage'!$A$15:$A$400) | I23: 4127680 | J23: TT 232/2012/TT-BTC Điều 12 (DT chi tiết theo nghiệp vụ); ACORD Coverage NetChangeAmt
A24: 20 | B24: core | C24: coinsurance_share | D24: Giao dịch | E24: Tỷ lệ tham gia đồng bảo hiểm của từng DNBH trên hợp đồng (tổng = 100%) | F24: 1 dòng / hợp đồng × DNBH | G24: insurer_code, policy_id | H24: =COUNT('core.coinsurance_share'!$A$15:$A$400) | I24: 4082967 | J24: Luật KDBH 2022 Điều 4 k29; TT 232/2012/TT-BTC Điều 19; TT 67/2023/TT-BTC Điều 41 k2
A25: 21 | B25: core | C25: revenue_allocation | D25: Giao dịch | E25: Phân bổ doanh thu phần của công ty cho các đơn vị (tổng = 100%) | F25: 1 dòng / hợp đồng × đơn vị | G25: company_code, policy_id | H25: =COUNT('core.revenue_allocation'!$A$15:$A$400) | I25: 4152252 | J25: Thông lệ quản trị Tổng công ty – công ty thành viên
C26: TỔNG | H26: =SUM(H5:H25) | I26: =SUM(I5:I25)
A28: Ghi chú: 'Số cột' là công thức COUNT trên sheet của từng bảng; 'Số dòng' đếm trên PostgreSQL sau khi nạp dữ liệu dummy.

Sheet Quan hệ FK
A1: Quan hệ khóa ngoại
A2: Sinh tự động từ catalog PostgreSQL reportapi — bronze.ins_* (scripts/build_docs.py, DOCS_TARGET=volume) ngày 19/10/2026. Tên bảng ghi theo mô hình logic: ref.X / core.X = bronze.ins_X.
A4: STT | B4: Bảng con | C4: Cột | D4: → Bảng cha | E4: Cột cha | F4: Ý nghĩa
A5: 1 | B5: ref.province | C5: region_code | D5: ref.region | E5: region_code | F5: Vùng của tỉnh → ref.region
A6: 2 | B6: ref.company | C6: parent_company_code | D6: ref.company | E6: company_code | F6: Đơn vị cấp trên → ref.company (NULL = Tổng công ty)
A7: 3 | B7: ref.company | C7: province_code | D7: ref.province | E7: province_code | F7: Tỉnh/thành đặt trụ sở → ref.province (NULL = đơn vị không gắn địa bàn)
A8: 4 | B8: ref.regulatory_line | C8: parent_line_code | D8: ref.regulatory_line | E8: report_line_code | F8: Dòng cha → ref.regulatory_line
A9: 5 | B9: ref.product_group | C9: lob_code | D9: ref.line_of_business | E9: lob_code | F9: Nghiệp vụ → ref.line_of_business
A10: 6 | B10: ref.product | C10: product_group_code | D10: ref.product_group | E10: product_group_code | F10: Nhóm sản phẩm → ref.product_group
A11: 7 | B11: ref.product | C11: report_line_code | D11: ref.regulatory_line | E11: report_line_code | F11: Dòng báo cáo Mẫu 2-PNT → ref.regulatory_line
A12: 8 | B12: ref.partner | C12: channel_code | D12: ref.channel | E12: channel_code | F12: Kênh của đối tác → ref.channel
A13: 9 | B13: ref.customer | C13: home_company_code | D13: ref.company | E13: company_code | F13: Đơn vị quản lý khách hàng → ref.company
A14: 10 | B14: ref.customer | C14: province_code | D14: ref.province | E14: province_code | F14: Tỉnh/thành → ref.province
A15: 11 | B15: ref.customer | C15: segment_code | D15: ref.customer_segment | E15: segment_code | F15: Phân khúc → ref.customer_segment
A16: 12 | B16: ref.fx_rate | C16: currency_code | D16: ref.currency | E16: currency_code | F16: Tiền tệ → ref.currency
... A31: 27 | B31: core.revenue_allocation | C31: policy_id | D31: core.policy | E31: policy_id | F31: Hợp đồng → core.policy

Sheet Quy tắc nghiệp vụ
A1: Quy tắc nghiệp vụ
A2: Sinh tự động từ catalog PostgreSQL reportapi — bronze.ins_* (scripts/build_docs.py, DOCS_TARGET=volume) ngày 19/10/2026. Tên bảng ghi theo mô hình logic: ref.X / core.X = bronze.ins_X.
A4: STT | B4: Quy tắc | C4: Diễn giải / công thức | D4: Căn cứ
A5: 1 | B5: Quy ước NULL & tham chiếu danh mục | C5: Lớp nguồn giữ NULL đúng nghiệp vụ: partner_code NULL = không qua đối tác (hợp lệ); channel_code NULL = nguồn thiếu kênh (lỗi dữ liệu). Mọi mã khác NULL đều có khóa ngoại đã kiểm chứng. Lớp phân tích (view) gán thành viên CHUA_XD / WEB_APP / KHONG_QUA_DT để dòng fact luôn tham chiếu được danh mục | D5: Quy ước dự án 13/10/2026
A6: 2 | B6: Đồng bảo hiểm | C6: Mỗi hợp đồng có ≥ 1 dòng core.coinsurance_share; tổng share_pct = 100. Đơn không đồng BH: 1 dòng insurer_code = 'OWN', role = 'SOLE', 100% | D6: Luật KDBH 2022 Điều 4 k29; TT 232/2012/TT-BTC Điều 19
A7: 3 | B7: Phân bổ doanh thu | C7: Mỗi hợp đồng có ≥ 1 dòng core.revenue_allocation; tổng allocation_pct = 100 | D7: Thông lệ quản trị Tổng công ty – công ty thành viên
A8: 4 | B8: Thời điểm ghi nhận doanh thu | C8: accounting_date = max(ngày cấp, ngày bắt đầu hiệu lực) với cấp mới/tái tục; = ngày chứng từ với SĐBS/hoàn/hủy | D8: TT 67/2023/TT-BTC Điều 41 k1 (phát sinh trách nhiệm bảo hiểm)
A9: 5 | B9: Khoản giảm thu | C9: Hoàn phí, giảm phí, hủy đơn có premium_orig âm; hạch toán TK 5311/5321 (ref.transaction_type.gl_account) | D9: NĐ 46/2023/NĐ-CP Điều 49 k3; TT 232/2012/TT-BTC
A10: 6 | B10: Trạng thái chứng từ | C10: status: APPROVED / PENDING / VOID — chỉ APPROVED là chứng từ hợp lệ để tính doanh thu | D10: Quy ước chuẩn: chỉ chứng từ đã duyệt là căn cứ ghi nhận; PENDING / VOID là kịch bản kiểm thử
A11: 7 | B11: Doanh thu Tổng công ty | C11: = tổng doanh thu hợp nhất mọi đơn vị; Khối Trụ sở (company_type = HEAD_OFFICE) là một đơn vị ngang cấp Công ty | D11: Quy ước chuẩn theo cấp phân tích của đề bài
A12: 8 | B12: Quy đổi ngoại tệ | C12: premium_vnd = premium_orig × fx_rate; fx_rate = tỷ giá hạch toán của tháng accounting_date (ref.fx_rate) | D12: Tỷ giá hạch toán KBNN
A13: 9 | B13: Thuế GTGT | C13: vat_vnd = premium_vnd × ref.product.vat_rate; BH con người 0% (không chịu thuế), xe/tài sản/cháy nổ 10% | D13: Luật GTGT 48/2024 Điều 5 k8, Điều 9
A14: 10 | B14: Hoa hồng | C14: commission_rate_pct ≤ ref.product.max_commission_pct; = 0 với bán trực tiếp và đấu thầu | D14: TT 67/2023/TT-BTC Điều 51
A15: 11 | B15: Biểu phí bắt buộc | C15: TNDS bắt buộc tính theo biểu phí cố định theo loại xe; cháy nổ bắt buộc theo tỷ lệ phí tối thiểu theo nhóm cơ sở | D15: NĐ 67/2023/NĐ-CP Phụ lục I, II
A16: 12 | B16: Cách tính doanh thu từ dữ liệu nguồn (tham khảo cho giai đoạn ETL) | C16: doanh thu = premium_vnd × share_pct('OWN')/100 × allocation_pct/100, chỉ status = APPROVED, kỳ theo accounting_date | D16: TT 232/2012/TT-BTC Điều 19; TT 67/2023/TT-BTC Điều 41
... A22: 18 | B22: Kiểm tra toàn vẹn | C22: 41 quy tắc nghiệp vụ (audit/consistency_checks.sql): hợp đồng, khách hàng, giao dịch, dòng phí, đồng BH, phân bổ, tham chiếu danh mục — kết quả mong đợi 0 vi phạm | D22: audit/run_audit.py

Sheet Kịch bản dữ liệu
A1: Kịch bản dữ liệu
A2: Sinh tự động từ catalog PostgreSQL reportapi — bronze.ins_* (scripts/build_docs.py, DOCS_TARGET=volume) ngày 19/10/2026. Tên bảng ghi theo mô hình logic: ref.X / core.X = bronze.ins_X.
A4: STT | B4: Tình huống | C4: Nhận diện trong dữ liệu | D4: Xử lý mong đợi
A5: 1 | B5: Đồng bảo hiểm (đứng đầu / tham gia) | C5: core.coinsurance_share có > 1 dòng / hợp đồng; role LEADER / FOLLOWER | D5: Chỉ phần 'OWN' là doanh thu của công ty
A6: 2 | B6: Phân bổ doanh thu nhiều đơn vị | C6: core.revenue_allocation: HO_TRO_CHEO, CHUYEN_GIAO | D6: Doanh thu theo đơn vị được phân bổ, khác đơn vị cấp đơn
A7: 3 | B7: Khối Trụ sở khai thác rủi ro lớn | C7: issuing_company_code = 'HO' (company_type = HEAD_OFFICE) | D7: Phân biệt doanh thu hợp nhất và doanh thu khối Trụ sở
A8: 4 | B8: SĐBS tăng / giảm phí, hoàn phí, hủy | C8: txn_type_code END_INC / END_DEC / REFUND / CANCEL | D8: Số âm/dương vào kỳ phát sinh; TK 5111/5311/5321
A9: 5 | B9: SĐBS không đổi phí | C9: txn_type_code END_NOCHG, premium = 0 | D9: Không ảnh hưởng doanh thu
A10: 6 | B10: Chứng từ chưa duyệt / hủy chứng từ | C10: status PENDING / VOID (~1,5%) | D10: Loại khỏi doanh thu
A11: 7 | B11: Hiệu lực sau ngày cấp (cả sang năm sau) | C11: effective_date > issue_date → accounting_date > txn_date | D11: Ghi nhận theo accounting_date, không theo ngày chứng từ
A12: 8 | B12: Hợp đồng ngoại tệ (USD) | C12: core.policy.currency_code = 'USD' | D12: Quy đổi theo fx_rate của giao dịch
A13: 9 | B13: Hợp đồng nhiều sản phẩm | C13: VCX ô tô + TNDS; cháy nổ BB + mọi rủi ro tài sản | D13: Tách doanh thu theo product_code
A14: 10 | B14: Đơn lô giấy chứng nhận / khách lẻ theo bảng kê | C14: is_group_policy; ref.customer.is_aggregated_retail | D14: Loại khi phân tích khách hàng định danh
A15: 11 | B15: Tái tục | C15: core.policy.renewal_of_policy_id | D15: Liên kết hợp đồng năm trước
A16: 12 | B16: Kênh chưa khai báo (~0,5%) | C16: core.policy.channel_code IS NULL | D16: Gán 'Chưa xác định'
A17: 13 | B17: Đơn vị không gắn địa bàn | C17: ref.company.province_code IS NULL (Trung tâm Kinh doanh số) | D17: Vùng miền để trống

Sheet ref.region
A1: ref.region — Vùng miền dùng để nhóm tỉnh/thành
A2: ← Về Tổng quan bảng
A4: Schema | B4: ref
A5: Bảng | B5: region
A6: Lớp | B6: Danh mục
A7: Mô tả | B7: Vùng miền dùng để nhóm tỉnh/thành
A8: Grain (1 dòng là gì) | B8: 1 dòng / vùng
A9: Khóa chính | B9: region_code
A10: Số cột | B10: =COUNT($A$15:$A$400)
A11: Số dòng (dummy) | B11: 3
A12: Căn cứ / chuẩn tham chiếu | B12: Đề xuất của dự án (không có văn bản pháp lý chia 3 miền)
A14: STT | B14: Cột | C14: Kiểu dữ liệu | D14: NOT NULL | E14: Khóa chính | F14: Khóa ngoại → | G14: UNIQUE | H14: Mô tả | I14: Căn cứ / nguồn | J14: Giá trị mẫu | K14: Số giá trị khác nhau | L14: % NULL
A15: 1 | B15: region_code | C15: character varying(10) | D15: ✓ | E15: PK | H15: Mã vùng: BAC / TRUNG / NAM | J15: BAC | NAM | TRUNG | K15: 3 | L15: 0
A16: 2 | B16: region_name | C16: character varying(50) | D16: ✓ | H16: Tên vùng | J16: Miền Bắc | Miền Nam | Miền Trung | K16: 3 | L16: 0
B19: Khóa ngoại — bảng này tham chiếu tới
B20: Cột | C20: → Bảng cha | D20: Cột cha | E20: Ý nghĩa
B21: (không có)
B23: Được tham chiếu bởi — bảng con trỏ tới bảng này
B24: Bảng con | C24: Cột | D24: → Cột của bảng này | E24: Ý nghĩa
B25: ref.province | C25: region_code | D25: region_code | E25: Vùng của tỉnh → ref.region
B27: Dữ liệu mẫu — 5 dòng đầu (sắp theo cột 'region_code')
B28: region_code | C28: region_name
B29: BAC | C29: Miền Bắc
B30: NAM | C30: Miền Nam
B31: TRUNG | C31: Miền Trung

Sheet ref.province
A1: ref.province — Tỉnh/thành phố theo đơn vị hành chính hiện hành (34 đơn vị)
A2: ← Về Tổng quan bảng
A4: Schema | B4: ref
A5: Bảng | B5: province
A6: Lớp | B6: Danh mục
A7: Mô tả | B7: Tỉnh/thành phố theo đơn vị hành chính hiện hành (34 đơn vị)
A8: Grain (1 dòng là gì) | B8: 1 dòng / tỉnh-thành
A9: Khóa chính | B9: province_code
A10: Số cột | B10: =COUNT($A$15:$A$400)
A11: Số dòng (dummy) | B11: 34
A12: Căn cứ / chuẩn tham chiếu | B12: NQ 202/2025/QH15
A14: STT | B14: Cột | C14: Kiểu dữ liệu | D14: NOT NULL | E14: Khóa chính | F14: Khóa ngoại → | G14: UNIQUE | H14: Mô tả | I14: Căn cứ / nguồn | J14: Giá trị mẫu | K14: Số giá trị khác nhau | L14: % NULL
A15: 1 | B15: province_code | C15: character varying(10) | D15: ✓ | E15: PK | H15: Mã tỉnh/thành (mã do dự án đặt, 3 ký tự) | J15: AGG | BNH | CBG | K15: 34 | L15: 0
A16: 2 | B16: province_name | C16: character varying(100) | D16: ✓ | H16: Tên tỉnh/thành phố | I16: NQ 202/2025/QH15 | J16: Thành phố Cần Thơ | Thành phố Đà Nẵng | Thành phố Hải Phòng | K16: 34 | L16: 0
A17: 3 | B17: region_code | C17: character varying(10) | D17: ✓ | F17: ref.region.region_code | H17: Vùng của tỉnh → ref.region | I17: Đề xuất của dự án | J17: BAC | NAM | TRUNG | K17: 3 | L17: 0
B20: Khóa ngoại — bảng này tham chiếu tới
B21: Cột | C21: → Bảng cha | D21: Cột cha | E21: Ý nghĩa
B22: region_code | C22: ref.region | D22: region_code | E22: Vùng của tỉnh → ref.region
B24: Được tham chiếu bởi — bảng con trỏ tới bảng này
B25: Bảng con | C25: Cột | D25: → Cột của bảng này | E25: Ý nghĩa
B26: ref.company | C26: province_code | D26: province_code | E26: Tỉnh/thành đặt trụ sở → ref.province (NULL = đơn vị không gắn địa bàn)
B27: ref.customer | C27: province_code | D27: province_code | E27: Tỉnh/thành → ref.province
B29: Dữ liệu mẫu — 5 dòng đầu (sắp theo cột 'province_code')
B30: province_code | C30: province_name | D30: region_code
B31: AGG | C31: Tỉnh An Giang | D31: NAM
B32: BNH | C32: Tỉnh Bắc Ninh | D32: BAC
B33: CBG | C33: Tỉnh Cao Bằng | D33: BAC
B34: CMU | C34: Tỉnh Cà Mau | D34: NAM
B35: CTO | C35: Thành phố Cần Thơ | D35: NAM

Sheet ref.company
A1: ref.company — Cơ cấu tổ chức: Tổng công ty → khối trụ sở, công ty thành viên, đơn vị kinh doanh số
A2: ← Về Tổng quan bảng
A4: Schema | B4: ref
A5: Bảng | B5: company
A6: Lớp | B6: Danh mục
A7: Mô tả | B7: Cơ cấu tổ chức: Tổng công ty → khối trụ sở, công ty thành viên, đơn vị kinh doanh số
A8: Grain (1 dòng là gì) | B8: 1 dòng / đơn vị
A9: Khóa chính | B9: company_code
A10: Số cột | B10: =COUNT($A$15:$A$400)
A11: Số dòng (dummy) | B11: 49
A12: Căn cứ / chuẩn tham chiếu | B12: Mô hình Tổng công ty – công ty thành viên công khai của các DNBH (BCTN Bảo Việt, PVI)
A14: STT | B14: Cột | C14: Kiểu dữ liệu | D14: NOT NULL | E14: Khóa chính | F14: Khóa ngoại → | G14: UNIQUE | H14: Mô tả | I14: Căn cứ / nguồn | J14: Giá trị mẫu | K14: Số giá trị khác nhau | L14: % NULL
A15: 1 | B15: company_code | C15: character varying(10) | D15: ✓ | E15: PK | H15: Mã đơn vị | J15: AGI | ALC | BTB | K15: 49 | L15: 0
A16: 2 | B16: company_name | C16: character varying(200) | D16: ✓ | H16: Tên đơn vị (giả lập, đặt theo địa bàn) | J16: Bảo hiểm PVI An Giang | Bảo hiểm PVI Âu Lạc | Bảo hiểm PVI Bắc Trung Bộ | K16: 49 | L16: 0
A17: 3 | B17: company_type | C17: character varying(20) | D17: ✓ | H17: Loại đơn vị: CORPORATION (Tổng công ty) / HEAD_OFFICE (khối trụ sở khai thác trực tiếp) / MEMBER (công ty thành viên) / DIGITAL (đơn vị kinh doanh số) | J17: CORPORATION | DIGITAL | HEAD_OFFICE | K17: 4 | L17: 0
A18: 4 | B18: parent_company_code | C18: character varying(10) | F18: ref.company.company_code | H18: Đơn vị cấp trên → ref.company (NULL = Tổng công ty) | J18: PVI | K18: 1 | L18: 0.020408163
A19: 5 | B19: province_code | C19: character varying(10) | F19: ref.province.province_code | H19: Tỉnh/thành đặt trụ sở → ref.province (NULL = đơn vị không gắn địa bàn) | J19: AGG | BNH | CMU | K19: 27 | L19: 0
A20: 6 | B20: established_date | C20: date | H20: Ngày thành lập (giả lập) | J20: 2005-01-01 | 2005-04-01 | 2005-07-01 | K20: 48 | L20: 0
B23: Khóa ngoại — bảng này tham chiếu tới
B24: Cột | C24: → Bảng cha | D24: Cột cha | E24: Ý nghĩa
B25: parent_company_code | C25: ref.company | D25: company_code | E25: Đơn vị cấp trên → ref.company (NULL = Tổng công ty)
B26: province_code | C26: ref.province | D26: province_code | E26: Tỉnh/thành đặt trụ sở → ref.province (NULL = đơn vị không gắn địa bàn)
B28: Được tham chiếu bởi — bảng con trỏ tới bảng này
B29: Bảng con | C29: Cột | D29: → Cột của bảng này | E29: Ý nghĩa
B30: core.policy | C30: issuing_company_code | D30: company_code | E30: Đơn vị cấp đơn → ref.company
B31: core.revenue_allocation | C31: company_code | D31: company_code | E31: Đơn vị được phân bổ doanh thu → ref.company
B32: ref.company | C32: parent_company_code | D32: company_code | E32: Đơn vị cấp trên → ref.company (NULL = Tổng công ty)
B33: ref.customer | C33: home_company_code | D33: company_code | E33: Đơn vị quản lý khách hàng → ref.company
B35: Dữ liệu mẫu — 5 dòng đầu (sắp theo cột 'company_code')
B36: company_code | C36: company_name | D36: company_type | E36: parent_company_code | F36: province_code | G36: established_date
B37: AGI | C37: Bảo hiểm PVI An Giang | D37: MEMBER | E37: PVI | F37: AGG | G37: 43709
B38: ALC | C38: Bảo hiểm PVI Âu Lạc | D38: MEMBER | E38: PVI | F38: HNI | G38: 41518
B39: BTB | C39: Bảo hiểm PVI Bắc Trung Bộ | D39: MEMBER | E39: PVI | F39: NAN | G39: 41214
B40: BTH | C40: Bảo hiểm PVI Bến Thành | D40: MEMBER | E40: PVI | F40: HCM | G40: 43221
B41: CLG | C41: Bảo hiểm PVI Cửu Long | D41: MEMBER | E41: PVI | F41: VLG | G41: 41334

Sheet ref.line_of_business
A1: ref.line_of_business — Nghiệp vụ bảo hiểm + nhóm phân tích POC (Xe / Con người / Tài sản)
A2: ← Về Tổng quan bảng
A4: Schema | B4: ref
A5: Bảng | B5: line_of_business
A6: Lớp | B6: Danh mục
A7: Mô tả | B7: Nghiệp vụ bảo hiểm + nhóm phân tích POC (Xe / Con người / Tài sản)
A8: Grain (1 dòng là gì) | B8: 1 dòng / nghiệp vụ
A9: Khóa chính | B9: lob_code
A10: Số cột | B10: =COUNT($A$15:$A$400)
A11: Số dòng (dummy) | B11: 4
A12: Căn cứ / chuẩn tham chiếu | B12: Luật KDBH 2022 Điều 7; NĐ 46/2023/NĐ-CP Điều 4–5
A14: STT | B14: Cột | C14: Kiểu dữ liệu | D14: NOT NULL | E14: Khóa chính | F14: Khóa ngoại → | G14: UNIQUE | H14: Mô tả | I14: Căn cứ / nguồn | J14: Giá trị mẫu | K14: Số giá trị khác nhau | L14: % NULL
A15: 1 | B15: lob_code | C15: character varying(10) | D15: ✓ | E15: PK | H15: Mã nghiệp vụ: SUC_KHOE / XE_CO_GIOI / CHAY_NO / TAI_SAN | J15: CHAY_NO | SUC_KHOE | TAI_SAN | K15: 4 | L15: 0
A16: 2 | B16: lob_name | C16: character varying(200) | D16: ✓ | H16: Tên nghiệp vụ | I16: NĐ 46/2023/NĐ-CP Điều 4–5 | J16: Bảo hiểm cháy, nổ | Bảo hiểm sức khỏe | Bảo hiểm tài sản | K16: 4 | L16: 0
A17: 3 | B17: legal_category | C17: character varying(100) | D17: ✓ | H17: Loại hình bảo hiểm: Bảo hiểm sức khỏe / Bảo hiểm phi nhân thọ | I17: Luật KDBH 2022 Điều 7 khoản 1 | J17: Bảo hiểm phi nhân thọ | Bảo hiểm sức khỏe | K17: 2 | L17: 0
A18: 4 | B18: poc_group_code | C18: character varying(20) | D18: ✓ | H18: Nhóm phân tích POC: XE / CON_NGUOI / TAI_SAN | I18: Đề bài POC | J18: CON_NGUOI | TAI_SAN | XE | K18: 3 | L18: 0
A19: 5 | B19: poc_group_name | C19: character varying(100) | D19: ✓ | H19: Tên nhóm phân tích POC | I19: Đề bài POC | J19: Con người | Tài sản | Xe cơ giới | K19: 3 | L19: 0
A20: 6 | B20: legal_basis | C20: character varying(300) | D20: ✓ | H20: Căn cứ pháp lý của nghiệp vụ | J20: Luật KDBH 2022 (08/2022/QH15) Điều 4 k15 | Luật KDBH 2022 (08/2022/QH15) Điều 7 k1 | K20: 2 | L20: 0
B23: Khóa ngoại — bảng này tham chiếu tới
B24: Cột | C24: → Bảng cha | D24: Cột cha | E24: Ý nghĩa
B25: (không có)
B27: Được tham chiếu bởi — bảng con trỏ tới bảng này
B28: Bảng con | C28: Cột | D28: → Cột của bảng này | E28: Ý nghĩa
B29: ref.product_group | C29: lob_code | D29: lob_code | E29: Nghiệp vụ → ref.line_of_business
B31: Dữ liệu mẫu — 5 dòng đầu (sắp theo cột 'lob_code')
B32: lob_code | C32: lob_name | D32: legal_category | E32: poc_group_code | F32: poc_group_name | G32: legal_basis
B33: CHAY_NO | C33: Bảo hiểm cháy, nổ | D33: Bảo hiểm phi nhân thọ | E33: TAI_SAN | F33: Tài sản | G33: Luật KDBH 2022 (08/2022/QH15) Điều 7 k1 điểm c; NĐ 46/2023/NĐ-CP Điều 4
B34: SUC_KHOE | C34: Bảo hiểm sức khỏe | D34: Bảo hiểm sức khỏe | E34: CON_NGUOI | F34: Con người | G34: Luật KDBH 2022 (08/2022/QH15) Điều 4 k15, Điều 7 k1 điểm b; NĐ 46/2023/NĐ-CP Điề
B35: TAI_SAN | C35: Bảo hiểm tài sản | D35: Bảo hiểm phi nhân thọ | E35: TAI_SAN | F35: Tài sản | G35: Luật KDBH 2022 (08/2022/QH15) Điều 7 k1 điểm c; NĐ 46/2023/NĐ-CP Điều 4
B36: XE_CO_GIOI | C36: Bảo hiểm xe cơ giới | D36: Bảo hiểm phi nhân thọ | E36: XE | F36: Xe cơ giới | G36: Luật KDBH 2022 (08/2022/QH15) Điều 7 k1 điểm c; NĐ 46/2023/NĐ-CP Điều 4

Sheet ref.regulatory_line
A1: ref.regulatory_line — Dòng báo cáo nghiệp vụ theo mẫu báo cáo Bộ Tài chính (cây cha–con)
A2: ← Về Tổng quan bảng
A4: Schema | B4: ref
A5: Bảng | B5: regulatory_line
A6: Lớp | B6: Danh mục
A7: Mô tả | B7: Dòng báo cáo nghiệp vụ theo mẫu báo cáo Bộ Tài chính (cây cha–con)
A8: Grain (1 dòng là gì) | B8: 1 dòng / dòng báo cáo
A9: Khóa chính | B9: report_line_code
A10: Số cột | B10: =COUNT($A$15:$A$400)
A11: Số dòng (dummy) | B11: 14
A12: Căn cứ / chuẩn tham chiếu | B12: TT 67/2023/TT-BTC Phụ lục VI – Mẫu 1-PNT/2-PNT
A14: STT | B14: Cột | C14: Kiểu dữ liệu | D14: NOT NULL | E14: Khóa chính | F14: Khóa ngoại → | G14: UNIQUE | H14: Mô tả | I14: Căn cứ / nguồn | J14: Giá trị mẫu | K14: Số giá trị khác nhau | L14: % NULL
A15: 1 | B15: report_line_code | C15: character varying(10) | D15: ✓ | E15: PK | H15: Mã dòng báo cáo (A.1, A.2, B.4a.1 …) — mã do dự án đặt theo thứ tự dòng trong mẫu | I15: TT 67/2023/TT-BTC Phụ lục VI | J15: A | A.1 | A.2 | K15: 14 | L15: 0
A16: 2 | B16: report_line_name | C16: character varying(200) | D16: ✓ | H16: Tên dòng báo cáo nghiệp vụ | I16: TT 67/2023/TT-BTC Phụ lục VI | J16: Bảo hiểm bắt buộc TNDS của chủ xe cơ giớ | Bảo hiểm cháy, nổ | Bảo hiểm cháy, nổ bắt buộc | K16: 14 | L16: 0
A17: 3 | B17: parent_line_code | C17: character varying(10) | F17: ref.regulatory_line.report_line_code | H17: Dòng cha → ref.regulatory_line | J17: A | B | B.1 | K17: 6 | L17: 0.14285714
A18: 4 | B18: legal_basis | C18: character varying(300) | D18: ✓ | H18: Căn cứ | J18: TT 67/2023/TT-BTC Phụ lục VI – Mẫu 1-PNT | K18: 1 | L18: 0
B21: Khóa ngoại — bảng này tham chiếu tới
B22: Cột | C22: → Bảng cha | D22: Cột cha | E22: Ý nghĩa
B23: parent_line_code | C23: ref.regulatory_line | D23: report_line_code | E23: Dòng cha → ref.regulatory_line
B25: Được tham chiếu bởi — bảng con trỏ tới bảng này
B26: Bảng con | C26: Cột | D26: → Cột của bảng này | E26: Ý nghĩa
B27: ref.product | C27: report_line_code | D27: report_line_code | E27: Dòng báo cáo Mẫu 2-PNT → ref.regulatory_line
B28: ref.regulatory_line | C28: parent_line_code | D28: report_line_code | E28: Dòng cha → ref.regulatory_line
B30: Dữ liệu mẫu — 5 dòng đầu (sắp theo cột 'report_line_code')
B31: report_line_code | C31: report_line_name | D31: parent_line_code | E31: legal_basis
B32: A | C32: Bảo hiểm sức khỏe | E32: TT 67/2023/TT-BTC Phụ lục VI – Mẫu 1-PNT/2-PNT
B33: A.1 | C33: Bảo hiểm sức khỏe, thân thể | D33: A | E33: TT 67/2023/TT-BTC Phụ lục VI – Mẫu 1-PNT/2-PNT
B34: A.2 | C34: Bảo hiểm chi phí y tế | D34: A | E34: TT 67/2023/TT-BTC Phụ lục VI – Mẫu 1-PNT/2-PNT
B35: B | C35: Bảo hiểm phi nhân thọ | E35: TT 67/2023/TT-BTC Phụ lục VI – Mẫu 1-PNT/2-PNT
B36: B.1 | C36: Bảo hiểm tài sản | D36: B | E36: TT 67/2023/TT-BTC Phụ lục VI – Mẫu 1-PNT/2-PNT

Sheet ref.product_group
A1: ref.product_group — Nhóm sản phẩm — cấp giữa Nghiệp vụ và Sản phẩm, đúng 8 nhóm của đề bài
A2: ← Về Tổng quan bảng
A4: Schema | B4: ref
A5: Bảng | B5: product_group
A6: Lớp | B6: Danh mục
A7: Mô tả | B7: Nhóm sản phẩm — cấp giữa Nghiệp vụ và Sản phẩm, đúng 8 nhóm của đề bài
A8: Grain (1 dòng là gì) | B8: 1 dòng / nhóm SP
A9: Khóa chính | B9: product_group_code
A10: Số cột | B10: =COUNT($A$15:$A$400)
A11: Số dòng (dummy) | B11: 8
A12: Căn cứ / chuẩn tham chiếu | B12: Phạm vi đề bài POC
A14: STT | B14: Cột | C14: Kiểu dữ liệu | D14: NOT NULL | E14: Khóa chính | F14: Khóa ngoại → | G14: UNIQUE | H14: Mô tả | I14: Căn cứ / nguồn | J14: Giá trị mẫu | K14: Số giá trị khác nhau | L14: % NULL
A15: 1 | B15: product_group_code | C15: character varying(20) | D15: ✓ | E15: PK | H15: Mã nhóm SP: TNDS_BB, VCX, HOC_SINH, DU_LICH, SINH_MANG, SUC_KHOE, TAI_SAN, CHAY_NO | I15: Đề bài POC | J15: CHAY_NO | DU_LICH | HOC_SINH | K15: 8 | L15: 0
A16: 2 | B16: product_group_name | C16: character varying(100) | D16: ✓ | H16: Tên nhóm sản phẩm | J16: BH bắt buộc TNDS chủ xe | BH cháy nổ | BH du lịch | K16: 8 | L16: 0
A17: 3 | B17: lob_code | C17: character varying(10) | D17: ✓ | F17: ref.line_of_business.lob_code | H17: Nghiệp vụ → ref.line_of_business | J17: CHAY_NO | SUC_KHOE | TAI_SAN | K17: 4 | L17: 0
A18: 4 | B18: sort_order | C18: integer | D18: ✓ | H18: Thứ tự hiển thị | J18: 1 | 2 | 3 | K18: 8 | L18: 0
B21: Khóa ngoại — bảng này tham chiếu tới
B22: Cột | C22: → Bảng cha | D22: Cột cha | E22: Ý nghĩa
B23: lob_code | C23: ref.line_of_business | D23: lob_code | E23: Nghiệp vụ → ref.line_of_business
B25: Được tham chiếu bởi — bảng con trỏ tới bảng này
B26: Bảng con | C26: Cột | D26: → Cột của bảng này | E26: Ý nghĩa
B27: ref.product | C27: product_group_code | D27: product_group_code | E27: Nhóm sản phẩm → ref.product_group
B29: Dữ liệu mẫu — 5 dòng đầu (sắp theo cột 'product_group_code')
B30: product_group_code | C30: product_group_name | D30: lob_code | E30: sort_order
B31: CHAY_NO | C31: BH cháy nổ | D31: CHAY_NO | E31: 8
B32: DU_LICH | C32: BH du lịch | D32: SUC_KHOE | E32: 4
B33: HOC_SINH | C33: BH học sinh – sinh viên | D33: SUC_KHOE | E33: 3
B34: SINH_MANG | C34: BH sinh mạng – tai nạn | D34: SUC_KHOE | E34: 5
B35: SUC_KHOE | C35: BH sức khỏe | D35: SUC_KHOE | E35: 6

Sheet ref.product
A1: ref.product — Sản phẩm bảo hiểm (phạm vi POC)
A2: ← Về Tổng quan bảng
A4: Schema | B4: ref
A5: Bảng | B5: product
A6: Lớp | B6: Danh mục
A7: Mô tả | B7: Sản phẩm bảo hiểm (phạm vi POC)
A8: Grain (1 dòng là gì) | B8: 1 dòng / sản phẩm
A9: Khóa chính | B9: product_code
A10: Số cột | B10: =COUNT($A$15:$A$400)
A11: Số dòng (dummy) | B11: 23
A12: Căn cứ / chuẩn tham chiếu | B12: NĐ 67/2023/NĐ-CP; Luật GTGT 48/2024; TT 67/2023/TT-BTC Điều 51
A14: STT | B14: Cột | C14: Kiểu dữ liệu | D14: NOT NULL | E14: Khóa chính | F14: Khóa ngoại → | G14: UNIQUE | H14: Mô tả | I14: Căn cứ / nguồn | J14: Giá trị mẫu | K14: Số giá trị khác nhau | L14: % NULL
A15: 1 | B15: product_code | C15: character varying(20) | D15: ✓ | E15: PK | H15: Mã sản phẩm (tiền tố XE_ / NG_ / TS_ / CHN_) | J15: CHN_BB | CHN_TN | MV_DELAYCARE | K15: 23 | L15: 0
A16: 2 | B16: product_name | C16: character varying(300) | D16: ✓ | H16: Tên sản phẩm theo cách gọi phổ biến của thị trường | I16: Website các DNBH | J16: Bảo hiểm bắt buộc trách nhiệm dân sự của | Bảo hiểm bắt buộc trách nhiệm dân sự của | Bảo hiểm bệnh hiểm nghèo – ung thư | K16: 23 | L16: 0
A17: 3 | B17: product_group_code | C17: character varying(20) | D17: ✓ | F17: ref.product_group.product_group_code | H17: Nhóm sản phẩm → ref.product_group | J17: CHAY_NO | DU_LICH | HOC_SINH | K17: 8 | L17: 0
A18: 4 | B18: report_line_code | C18: character varying(10) | D18: ✓ | F18: ref.regulatory_line.report_line_code | H18: Dòng báo cáo Mẫu 2-PNT → ref.regulatory_line | I18: TT 67/2023/TT-BTC Phụ lục VI | J18: A.1 | A.2 | B.1b | K18: 8 | L18: 0
A19: 5 | B19: is_compulsory | C19: boolean | D19: ✓ | H19: TRUE = bảo hiểm bắt buộc | I19: NĐ 67/2023/NĐ-CP | J19: false | true | K19: 2 | L19: 0
A20: 6 | B20: pricing_basis | C20: character varying(20) | D20: ✓ | H20: Cách tính phí: TARIFF (biểu phí cố định) / RATE_ON_SI (% số tiền BH) / PER_PERSON (theo đầu người) | J20: PER_PERSON | RATE_ON_SI | TARIFF | K20: 3 | L20: 0
A21: 7 | B21: vat_rate | C21: numeric(5,2) | D21: ✓ | H21: Thuế suất GTGT %: 0 = không chịu thuế (BH con người), 10 = còn lại | I21: Luật GTGT 48/2024/QH15 Điều 5 khoản 8, Điều 9 | J21: 0.00 | 10.00 | K21: 2 | L21: 0
A22: 8 | B22: max_commission_pct | C22: numeric(5,2) | D22: ✓ | H22: Trần tỷ lệ hoa hồng đại lý % | I22: TT 67/2023/TT-BTC Điều 51 khoản 3 | J22: 10.00 | 20.00 | 5.00 | K22: 3 | L22: 0
A23: 9 | B23: legal_basis | C23: character varying(300) | H23: Căn cứ pháp lý riêng của sản phẩm (nếu có) | J23: Không chịu thuế GTGT – Luật Thuế GTGT 48 | NĐ 67/2023/NĐ-CP Phụ lục I (biểu phí TND | NĐ 67/2023/NĐ-CP Phụ lục II; thay thế bở | K23: 3 | L23: 0.30434783
A24: 10 | B24: solvency2_lob | C24: character varying(60) | D24: ✓ | H24: Đối chiếu quốc tế: Solvency II LoB; (*) = suy luận theo bản chất rủi ro | I24: Delegated Reg. (EU) 2015/35 Annex I | J24: 12 Miscellaneous financial loss (*) | 1 Medical expense insurance | 1 Medical expense insurance (*) | K24: 8 | L24: 0
B27: Khóa ngoại — bảng này tham chiếu tới
B28: Cột | C28: → Bảng cha | D28: Cột cha | E28: Ý nghĩa
B29: product_group_code | C29: ref.product_group | D29: product_group_code | E29: Nhóm sản phẩm → ref.product_group
B30: report_line_code | C30: ref.regulatory_line | D30: report_line_code | E30: Dòng báo cáo Mẫu 2-PNT → ref.regulatory_line
B32: Được tham chiếu bởi — bảng con trỏ tới bảng này
B33: Bảng con | C33: Cột | D33: → Cột của bảng này | E33: Ý nghĩa
B34: core.transaction_coverage | C34: product_code | D34: product_code | E34: Sản phẩm → ref.product
B36: Dữ liệu mẫu — 5 dòng đầu (sắp theo cột 'product_code')
B37: product_code | C37: product_name | D37: product_group_code | E37: report_line_code | F37: is_compulsory | G37: pricing_basis | H37: vat_rate | I37: max_commission_pct | J37: legal_basis | K37: solvency2_lob
B38: CHN_BB | C38: Bảo hiểm cháy, nổ bắt buộc | D38: CHAY_NO | E38: B.5a | F38: TRUE | G38: RATE_ON_SI | H38: 10 | I38: 5 | J38: NĐ 67/2023/NĐ-CP Phụ lục II; thay thế bởi NĐ 105/2025/NĐ-CP Phụ lục VI từ 01/7/2 | K38: 7 Fire and other damage to property insurance
B39: CHN_TN | C39: Bảo hiểm cháy và các rủi ro đặc biệt (tự nguyện) | D39: CHAY_NO | E39: B.5b | F39: FALSE | G39: RATE_ON_SI | H39: 10 | I39: 10 | K39: 7 Fire and other damage to property insurance
B40: MV_DELAYCARE | C40: Bảo hiểm trễ chuyến bay (DelayCare) | D40: DU_LICH | E40: A.2 | F40: FALSE | G40: PER_PERSON | H40: 0 | I40: 20 | J40: Không chịu thuế GTGT – Luật Thuế GTGT 48/2024/QH15 Điều 5 k8 | K40: 12 Miscellaneous financial loss (*)
B41: MV_FOOD_CARE | C41: Bảo hiểm đơn giao đồ ăn (Food Care) | D41: SINH_MANG | E41: A.1 | F41: FALSE | G41: PER_PERSON | H41: 0 | I41: 20 | J41: Không chịu thuế GTGT – Luật Thuế GTGT 48/2024/QH15 Điều 5 k8 | K41: 2 Income protection insurance (*)
B42: MV_TBDT_TMDT | C42: Bảo hiểm thiết bị điện tử mua trên sàn TMĐT | D42: TAI_SAN | E42: B.1b | F42: FALSE | G42: RATE_ON_SI | H42: 10 | I42: 5 | K42: 7 Fire and other damage to property insurance (*)

Sheet ref.channel
A1: ref.channel — Kênh phân phối theo hình thức cung cấp sản phẩm bảo hiểm
A2: ← Về Tổng quan bảng
A4: Schema | B4: ref
A5: Bảng | B5: channel
A6: Lớp | B6: Danh mục
A7: Mô tả | B7: Kênh phân phối theo hình thức cung cấp sản phẩm bảo hiểm
A8: Grain (1 dòng là gì) | B8: 1 dòng / kênh
A9: Khóa chính | B9: channel_code
A10: Số cột | B10: =COUNT($A$15:$A$400)
A11: Số dòng (dummy) | B11: 7
A12: Căn cứ / chuẩn tham chiếu | B12: Luật KDBH 2022 Điều 87 khoản 4; TT 67/2023/TT-BTC Mẫu 3-PNT
A14: STT | B14: Cột | C14: Kiểu dữ liệu | D14: NOT NULL | E14: Khóa chính | F14: Khóa ngoại → | G14: UNIQUE | H14: Mô tả | I14: Căn cứ / nguồn | J14: Giá trị mẫu | K14: Số giá trị khác nhau | L14: % NULL
A15: 1 | B15: channel_code | C15: character varying(20) | D15: ✓ | E15: PK | H15: Mã kênh: TRUC_TIEP, DAI_LY_CN, DAI_LY_TC, BANCA, MOI_GIOI, DAU_THAU, DIEN_TU | J15: BANCA | DAI_LY_CN | DAI_LY_TC | K15: 7 | L15: 0
A16: 2 | B16: channel_name | C16: character varying(150) | D16: ✓ | H16: Tên kênh | I16: Luật KDBH 2022 Điều 87 khoản 4 | J16: Bancassurance (đại lý là tổ chức tín dụn | Bán trực tiếp | Đại lý cá nhân | K16: 7 | L16: 0
A17: 3 | B17: report_channel_group | C17: character varying(100) | D17: ✓ | H17: Nhóm kênh báo cáo: Qua tổ chức tín dụng / Qua môi trường mạng / Qua kênh phân phối khác | I17: TT 67/2023/TT-BTC Mẫu 3-PNT | J17: Qua kênh phân phối khác | Qua môi trường mạng | Qua tổ chức tín dụng | K17: 3 | L17: 0
A18: 4 | B18: legal_basis | C18: character varying(300) | D18: ✓ | H18: Căn cứ pháp lý của kênh | J18: Luật KDBH 2022 (08/2022/QH15) Điều 87 k4 | Luật KDBH 2022 (08/2022/QH15) Điều 87 k4 | Luật KDBH 2022 (08/2022/QH15) Điều 87 k4 | K18: 6 | L18: 0
A19: 5 | B19: sort_order | C19: character varying(10) | D19: ✓ | H19: Thứ tự hiển thị | J19: 1 | 2 | 3 | K19: 7 | L19: 0
B22: Khóa ngoại — bảng này tham chiếu tới
B23: Cột | C23: → Bảng cha | D23: Cột cha | E23: Ý nghĩa
B24: (không có)
B26: Được tham chiếu bởi — bảng con trỏ tới bảng này
B27: Bảng con | C27: Cột | D27: → Cột của bảng này | E27: Ý nghĩa
B28: core.policy | C28: channel_code | D28: channel_code | E28: Kênh bán → ref.channel. Bắt buộc theo nghiệp vụ; NULL = nguồn không khai báo (~0
B29: ref.partner | C29: channel_code | D29: channel_code | E29: Kênh của đối tác → ref.channel
B31: Dữ liệu mẫu — 5 dòng đầu (sắp theo cột 'channel_code')
B32: channel_code | C32: channel_name | D32: report_channel_group | E32: legal_basis | F32: sort_order
B33: BANCA | C33: Bancassurance (đại lý là tổ chức tín dụng) | D33: Qua tổ chức tín dụng | E33: Luật KDBH 2022 (08/2022/QH15) Điều 87 k4 điểm b, Điều 125 k2; NĐ 46/2023/NĐ-CP Đ | F33: 4
B34: DAI_LY_CN | C34: Đại lý cá nhân | D34: Qua kênh phân phối khác | E34: Luật KDBH 2022 (08/2022/QH15) Điều 87 k4 điểm b; Điều 124 | F34: 2
B35: DAI_LY_TC | C35: Đại lý tổ chức | D35: Qua kênh phân phối khác | E35: Luật KDBH 2022 (08/2022/QH15) Điều 87 k4 điểm b; Điều 124 | F35: 3
B36: DAU_THAU | C36: Đấu thầu | D36: Qua kênh phân phối khác | E36: Luật KDBH 2022 (08/2022/QH15) Điều 87 k4 điểm c | F36: 6
B37: DIEN_TU | C37: Giao dịch điện tử (website/app, nền tảng đối tác) | D37: Qua môi trường mạng | E37: Luật KDBH 2022 (08/2022/QH15) Điều 87 k4 điểm d; TT 67/2023/TT-BTC Điều 4–5 | F37: 7

Sheet ref.partner
A1: ref.partner — Đối tác phân phối — ngân hàng, đăng kiểm, OTA, ví điện tử... (ẩn danh); 3 đối tác số tên thật có công bố hợp tác với PVI: Green SM, ATADI, Fuse
A2: ← Về Tổng quan bảng
A4: Schema | B4: ref
A5: Bảng | B5: partner
A6: Lớp | B6: Danh mục
A7: Mô tả | B7: Đối tác phân phối — ngân hàng, đăng kiểm, OTA, ví điện tử... (ẩn danh); 3 đối tác số tên thật có công bố hợp tác với PVI: Green SM, ATADI, Fuse
A8: Grain (1 dòng là gì) | B8: 1 dòng / đối tác
A9: Khóa chính | B9: partner_code
A10: Số cột | B10: =COUNT($A$15:$A$400)
A11: Số dòng (dummy) | B11: 39
A12: Căn cứ / chuẩn tham chiếu | B12: Loại đối tác theo thực tế thị trường; đối tác truyền thống ẩn danh, đối tác bảo hiểm vi mô theo nguồn công khai (sources/market_data.md mục 10)
A14: STT | B14: Cột | C14: Kiểu dữ liệu | D14: NOT NULL | E14: Khóa chính | F14: Khóa ngoại → | G14: UNIQUE | H14: Mô tả | I14: Căn cứ / nguồn | J14: Giá trị mẫu | K14: Số giá trị khác nhau | L14: % NULL
A15: 1 | B15: partner_code | C15: character varying(20) | D15: ✓ | E15: PK | H15: Mã đối tác | J15: ATADI | BC_A | CTTC_A | K15: 39 | L15: 0
A16: 2 | B16: partner_name | C16: character varying(200) | D16: ✓ | H16: Tên đối tác (ẩn danh: Ngân hàng TMCP A, Ví điện tử B …; tên thật cho Green SM, ATADI, Fuse) | J16: ATADI.vn – đại lý vé máy bay trực tuyến | Công ty lữ hành A | Công ty lữ hành B | K16: 39 | L16: 0
A17: 3 | B17: partner_type | C17: character varying(30) | D17: ✓ | H17: Loại đối tác: NGAN_HANG, CTY_TAI_CHINH, DANG_KIEM, SHOWROOM_OTO, GARAGE, OTA_DU_LICH, CTY_LU_HANH, CTY_MOI_GIOI, VI_DIEN_TU, SAN_TMDT, HANG_HANG_KHONG, VIEN_THONG | J17: BUU_CHINH | CTY_LU_HANH | CTY_MOI_GIOI | K17: 17 | L17: 0
A18: 4 | B18: channel_code | C18: character varying(20) | D18: ✓ | F18: ref.channel.channel_code | H18: Kênh của đối tác → ref.channel | J18: BANCA | DAI_LY_TC | DIEN_TU | K18: 4 | L18: 0
B21: Khóa ngoại — bảng này tham chiếu tới
B22: Cột | C22: → Bảng cha | D22: Cột cha | E22: Ý nghĩa
B23: channel_code | C23: ref.channel | D23: channel_code | E23: Kênh của đối tác → ref.channel
B25: Được tham chiếu bởi — bảng con trỏ tới bảng này
B26: Bảng con | C26: Cột | D26: → Cột của bảng này | E26: Ý nghĩa
B27: core.policy | C27: partner_code | D27: partner_code | E27: Đối tác phân phối → ref.partner. Không bắt buộc: NULL = không qua đối tác (bán t
B29: Dữ liệu mẫu — 5 dòng đầu (sắp theo cột 'partner_code')
B30: partner_code | C30: partner_name | D30: partner_type | E30: channel_code
B31: ATADI | C31: ATADI.vn – đại lý vé máy bay trực tuyến | D31: OTA_VE_MAY_BAY | E31: DIEN_TU
B32: BC_A | C32: Mạng lưới bưu cục A | D32: BUU_CHINH | E32: DAI_LY_TC
B33: CTTC_A | C33: Công ty tài chính A | D33: CTY_TAI_CHINH | E33: BANCA
B34: CTTC_B | C34: Công ty tài chính B | D34: CTY_TAI_CHINH | E34: BANCA
B35: DK_A | C35: Trung tâm đăng kiểm A | D35: DANG_KIEM | E35: DAI_LY_TC

Sheet ref.customer_segment
A1: ref.customer_segment — Phân khúc khách hàng
A2: ← Về Tổng quan bảng
A4: Schema | B4: ref
A5: Bảng | B5: customer_segment
A6: Lớp | B6: Danh mục
A7: Mô tả | B7: Phân khúc khách hàng
A8: Grain (1 dòng là gì) | B8: 1 dòng / phân khúc
A9: Khóa chính | B9: segment_code
A10: Số cột | B10: =COUNT($A$15:$A$400)
A11: Số dòng (dummy) | B11: 6
A12: Căn cứ / chuẩn tham chiếu | B12: Phân loại phổ biến (cá nhân / hộ gia đình / doanh nghiệp / cơ quan NN / cơ sở giáo dục)
A14: STT | B14: Cột | C14: Kiểu dữ liệu | D14: NOT NULL | E14: Khóa chính | F14: Khóa ngoại → | G14: UNIQUE | H14: Mô tả | I14: Căn cứ / nguồn | J14: Giá trị mẫu | K14: Số giá trị khác nhau | L14: % NULL
A15: 1 | B15: segment_code | C15: character varying(20) | D15: ✓ | E15: PK | H15: Mã phân khúc | J15: CA_NHAN | CO_QUAN_NN | CO_SO_GD | K15: 6 | L15: 0
A16: 2 | B16: segment_name | C16: character varying(100) | D16: ✓ | H16: Tên phân khúc | J16: Cá nhân | Cơ quan, đơn vị sự nghiệp nhà nước | Cơ sở giáo dục | K16: 6 | L16: 0
A17: 3 | B17: is_organization | C17: boolean | D17: ✓ | H17: TRUE = tổ chức, FALSE = cá nhân / hộ gia đình | J17: false | true | K17: 2 | L17: 0
B20: Khóa ngoại — bảng này tham chiếu tới
B21: Cột | C21: → Bảng cha | D21: Cột cha | E21: Ý nghĩa
B22: (không có)
B24: Được tham chiếu bởi — bảng con trỏ tới bảng này
B25: Bảng con | C25: Cột | D25: → Cột của bảng này | E25: Ý nghĩa
B26: ref.customer | C26: segment_code | D26: segment_code | E26: Phân khúc → ref.customer_segment
B28: Dữ liệu mẫu — 5 dòng đầu (sắp theo cột 'segment_code')
B29: segment_code | C29: segment_name | D29: is_organization
B30: CA_NHAN | C30: Cá nhân | D30: FALSE
B31: CO_QUAN_NN | C31: Cơ quan, đơn vị sự nghiệp nhà nước | D31: TRUE
B32: CO_SO_GD | C32: Cơ sở giáo dục | D32: TRUE
B33: DN_FDI | C33: Doanh nghiệp có vốn đầu tư nước ngoài | D33: TRUE
B34: DN_TRONG_NUOC | C34: Doanh nghiệp trong nước | D34: TRUE

Sheet ref.customer
A1: ref.customer — Khách hàng — bên mua bảo hiểm (dữ liệu giả)
A2: ← Về Tổng quan bảng
A4: Schema | B4: ref
A5: Bảng | B5: customer
A6: Lớp | B6: Danh mục
A7: Mô tả | B7: Khách hàng — bên mua bảo hiểm (dữ liệu giả)
A8: Grain (1 dòng là gì) | B8: 1 dòng / khách hàng
A9: Khóa chính | B9: customer_code
A10: Số cột | B10: =COUNT($A$15:$A$400)
A11: Số dòng (dummy) | B11: 1696375
A12: Căn cứ / chuẩn tham chiếu | B12: Dữ liệu sinh ngẫu nhiên
A14: STT | B14: Cột | C14: Kiểu dữ liệu | D14: NOT NULL | E14: Khóa chính | F14: Khóa ngoại → | G14: UNIQUE | H14: Mô tả | I14: Căn cứ / nguồn | J14: Giá trị mẫu | K14: Số giá trị khác nhau | L14: % NULL
A15: 1 | B15: customer_code | C15: character varying(20) | D15: ✓ | E15: PK | H15: Mã khách hàng (KHnnnnnnn) | J15: KH610000001 | KH610000002 | KH610000003 | K15: 1696375 | L15: 0
A16: 2 | B16: customer_name | C16: character varying(200) | D16: ✓ | H16: Tên khách hàng (giả) | I16: Dữ liệu sinh ngẫu nhiên | J16: Ban Quản lý dự án Bắc Ninh | Ban Quản lý dự án Cà Mau | Ban Quản lý dự án Cần Thơ | K16: 48530 | L16: 0
A17: 3 | B17: segment_code | C17: character varying(20) | D17: ✓ | F17: ref.customer_segment.segment_code | H17: Phân khúc → ref.customer_segment | J17: CA_NHAN | CO_QUAN_NN | CO_SO_GD | K17: 6 | L17: 0
A18: 4 | B18: tax_code | C18: character varying(20) | H18: Mã số thuế (chỉ tổ chức; giả) | J18: 0100037302 | 0100065094 | 0100068691 | K18: 15879 | L18: 0.99063945
A19: 5 | B19: province_code | C19: character varying(10) | F19: ref.province.province_code | H19: Tỉnh/thành → ref.province | J19: AGG | BNH | CBG | K19: 34 | L19: 0
A20: 6 | B20: home_company_code | C20: character varying(10) | D20: ✓ | F20: ref.company.company_code | H20: Đơn vị quản lý khách hàng → ref.company | J20: AGI | ALC | BTB | K20: 46 | L20: 0
A21: 7 | B21: is_aggregated_retail | C21: boolean | D21: ✓ | H21: TRUE = 'Khách lẻ theo bảng kê' — bên mua gộp của đơn lô giấy chứng nhận bán qua đối tác | J21: false | true | K21: 2 | L21: 0
A22: 8 | B22: created_date | C22: date | D22: ✓ | H22: Ngày tạo khách hàng | J22: 2015-01-01 | 2015-01-02 | 2015-01-03 | K22: 4291 | L22: 0
A23: 9 | B23: gender | C23: character(1) | H23: Giới tính M / F — chỉ khách cá nhân, hộ gia đình (NULL với tổ chức) | I23: Dữ liệu sinh ngẫu nhiên | J23: F | M | K23: 2 | L23: 0.0093876649
A24: 10 | B24: birth_year | C24: smallint | H24: Năm sinh — chỉ khách cá nhân, hộ gia đình; bên mua ≥ 18 tuổi | I24: Dữ liệu sinh ngẫu nhiên | J24: 1945 | 1946 | 1947 | K24: 63 | L24: 0.0093876649
B27: Khóa ngoại — bảng này tham chiếu tới
B28: Cột | C28: → Bảng cha | D28: Cột cha | E28: Ý nghĩa
B29: segment_code | C29: ref.customer_segment | D29: segment_code | E29: Phân khúc → ref.customer_segment
B30: province_code | C30: ref.province | D30: province_code | E30: Tỉnh/thành → ref.province
B31: home_company_code | C31: ref.company | D31: company_code | E31: Đơn vị quản lý khách hàng → ref.company
B33: Được tham chiếu bởi — bảng con trỏ tới bảng này
B34: Bảng con | C34: Cột | D34: → Cột của bảng này | E34: Ý nghĩa
B35: core.policy | C35: customer_code | D35: customer_code | E35: Bên mua bảo hiểm → ref.customer
B37: Dữ liệu mẫu — 5 dòng đầu (sắp theo cột 'customer_code')
B38: customer_code | C38: customer_name | D38: segment_code | E38: tax_code | F38: province_code | G38: home_company_code | H38: is_aggregated_retail | I38: created_date | J38: gender | K38: birth_year
B39: KH610000001 | C39: Hoàng Gia Nam | D39: CA_NHAN | F39: HPG | G39: DHI | H39: FALSE | I39: 46107 | J39: M | K39: 1974
B40: KH610000002 | C40: Đoàn Văn Phong | D40: CA_NHAN | F40: HNI | G40: HNO | H40: FALSE | I40: 43560 | J40: M | K40: 1987
B41: KH610000003 | C41: Hoàng Thanh Quyên | D41: CA_NHAN | F41: NAN | G41: BTB | H41: FALSE | I41: 44289 | J41: F | K41: 1988
B42: KH610000004 | C42: Vũ Tuấn Khoa | D42: CA_NHAN | F42: HCM | G42: TDH | H42: FALSE | I42: 46235 | J42: M | K42: 1977
B43: KH610000005 | C43: Nguyễn Công Tài | D43: CA_NHAN | F43: VLG | G43: CLG | H43: FALSE | I43: 46235 | J43: M | K43: 1968

Sheet ref.currency
A1: ref.currency — Tiền tệ
A2: ← Về Tổng quan bảng
A4: Schema | B4: ref
A5: Bảng | B5: currency
A6: Lớp | B6: Danh mục
A7: Mô tả | B7: Tiền tệ
A8: Grain (1 dòng là gì) | B8: 1 dòng / loại tiền
A9: Khóa chính | B9: currency_code
A10: Số cột | B10: =COUNT($A$15:$A$400)
A11: Số dòng (dummy) | B11: 2
A12: Căn cứ / chuẩn tham chiếu | B12: ISO 4217
A14: STT | B14: Cột | C14: Kiểu dữ liệu | D14: NOT NULL | E14: Khóa chính | F14: Khóa ngoại → | G14: UNIQUE | H14: Mô tả | I14: Căn cứ / nguồn | J14: Giá trị mẫu | K14: Số giá trị khác nhau | L14: % NULL
A15: 1 | B15: currency_code | C15: character(3) | D15: ✓ | E15: PK | H15: Mã tiền tệ ISO 4217 | J15: USD | VND | K15: 2 | L15: 0
A16: 2 | B16: currency_name | C16: character varying(50) | D16: ✓ | H16: Tên tiền tệ | J16: Đô la Mỹ | Đồng Việt Nam | K16: 2 | L16: 0
B19: Khóa ngoại — bảng này tham chiếu tới
B20: Cột | C20: → Bảng cha | D20: Cột cha | E20: Ý nghĩa
B21: (không có)
B23: Được tham chiếu bởi — bảng con trỏ tới bảng này
B24: Bảng con | C24: Cột | D24: → Cột của bảng này | E24: Ý nghĩa
B25: core.policy | C25: currency_code | D25: currency_code | E25: Loại tiền của hợp đồng → ref.currency
B26: ref.fx_rate | C26: currency_code | D26: currency_code | E26: Tiền tệ → ref.currency
B28: Dữ liệu mẫu — 5 dòng đầu (sắp theo cột 'currency_code')
B29: currency_code | C29: currency_name
B30: USD | C30: Đô la Mỹ
B31: VND | C31: Đồng Việt Nam

Sheet ref.fx_rate
A1: ref.fx_rate — Tỷ giá hạch toán theo tháng
A2: ← Về Tổng quan bảng
A4: Schema | B4: ref
A5: Bảng | B5: fx_rate
A6: Lớp | B6: Danh mục
A7: Mô tả | B7: Tỷ giá hạch toán theo tháng
A8: Grain (1 dòng là gì) | B8: 1 dòng / loại tiền × tháng
A9: Khóa chính | B9: currency_code, rate_month
A10: Số cột | B10: =COUNT($A$15:$A$400)
A11: Số dòng (dummy) | B11: 60
A12: Căn cứ / chuẩn tham chiếu | B12: Tỷ giá hạch toán KBNN 2025; 2024 ước tính
A14: STT | B14: Cột | C14: Kiểu dữ liệu | D14: NOT NULL | E14: Khóa chính | F14: Khóa ngoại → | G14: UNIQUE | H14: Mô tả | I14: Căn cứ / nguồn | J14: Giá trị mẫu | K14: Số giá trị khác nhau | L14: % NULL
A15: 1 | B15: currency_code | C15: character(3) | D15: ✓ | E15: PK | F15: ref.currency.currency_code | H15: Tiền tệ → ref.currency | J15: USD | K15: 1 | L15: 0
A16: 2 | B16: rate_month | C16: date | D16: ✓ | E16: PK | H16: Tháng áp dụng (ngày đầu tháng) | J16: 2024-01-01 | 2024-02-01 | 2024-03-01 | K16: 60 | L16: 0
A17: 3 | B17: rate_to_vnd | C17: numeric(18,2) | D17: ✓ | H17: Tỷ giá quy đổi ra VND | I17: Tỷ giá hạch toán KBNN | J17: 23880.00 | 23910.00 | 23960.00 | K17: 34 | L17: 0
A18: 4 | B18: source_note | C18: character varying(200) | D18: ✓ | H18: Ghi chú nguồn tỷ giá | J18: Tỷ giá hạch toán KBNN | Ước tính (bám xu hướng tỷ giá hạch toán | Ước tính nội suy tỷ giá trung tâm NHNN | K18: 3 | L18: 0
B21: Khóa ngoại — bảng này tham chiếu tới
B22: Cột | C22: → Bảng cha | D22: Cột cha | E22: Ý nghĩa
B23: currency_code | C23: ref.currency | D23: currency_code | E23: Tiền tệ → ref.currency
B25: Được tham chiếu bởi — bảng con trỏ tới bảng này
B26: Bảng con | C26: Cột | D26: → Cột của bảng này | E26: Ý nghĩa
B27: (không có)
B29: Dữ liệu mẫu — 5 dòng đầu (sắp theo cột 'currency_code')
B30: currency_code | C30: rate_month | D30: rate_to_vnd | E30: source_note
B31: USD | C31: 45292 | D31: 23880 | E31: Ước tính nội suy tỷ giá trung tâm NHNN
B32: USD | C32: 45323 | D32: 23910 | E32: Ước tính nội suy tỷ giá trung tâm NHNN
B33: USD | C33: 45352 | D33: 23960 | E33: Ước tính nội suy tỷ giá trung tâm NHNN
B34: USD | C34: 45383 | D34: 24000 | E34: Ước tính nội suy tỷ giá trung tâm NHNN
B35: USD | C35: 45413 | D35: 24180 | E35: Ước tính nội suy tỷ giá trung tâm NHNN

Sheet ref.transaction_type
A1: ref.transaction_type — Loại giao dịch phí: cấp mới, tái tục, SĐBS, hoàn phí, hủy
A2: ← Về Tổng quan bảng
A4: Schema | B4: ref
A5: Bảng | B5: transaction_type
A6: Lớp | B6: Danh mục
A7: Mô tả | B7: Loại giao dịch phí: cấp mới, tái tục, SĐBS, hoàn phí, hủy
A8: Grain (1 dòng là gì) | B8: 1 dòng / loại giao dịch
A9: Khóa chính | B9: txn_type_code
A10: Số cột | B10: =COUNT($A$15:$A$400)
A11: Số dòng (dummy) | B11: 7
A12: Căn cứ / chuẩn tham chiếu | B12: NĐ 46/2023/NĐ-CP Điều 49; TT 232/2012/TT-BTC; ACORD BusinessPurposeTypeCd
A14: STT | B14: Cột | C14: Kiểu dữ liệu | D14: NOT NULL | E14: Khóa chính | F14: Khóa ngoại → | G14: UNIQUE | H14: Mô tả | I14: Căn cứ / nguồn | J14: Giá trị mẫu | K14: Số giá trị khác nhau | L14: % NULL
A15: 1 | B15: txn_type_code | C15: character varying(20) | D15: ✓ | E15: PK | H15: Mã loại giao dịch: NEW, RENEW, END_INC, END_DEC, REFUND, CANCEL, END_NOCHG | J15: CANCEL | END_DEC | END_INC | K15: 7 | L15: 0
A16: 2 | B16: txn_type_name | C16: character varying(100) | D16: ✓ | H16: Tên loại giao dịch | J16: Cấp mới | Hoàn phí | Hủy hợp đồng (hoàn phí thời gian còn lại | K16: 7 | L16: 0
A17: 3 | B17: premium_sign | C17: smallint | D17: ✓ | H17: Dấu của phí: +1 / -1 / 0 | J17: 0 | -1 | 1 | K17: 3 | L17: 0
A18: 4 | B18: is_revenue_deduction | C18: boolean | D18: ✓ | H18: TRUE = khoản giảm thu (hoàn phí, giảm phí) | I18: NĐ 46/2023/NĐ-CP Điều 49 khoản 3 | J18: false | true | K18: 2 | L18: 0
A19: 5 | B19: gl_account | C19: character varying(10) | H19: Tài khoản kế toán: 5111 phí gốc / 5311 hoàn phí gốc / 5321 giảm phí gốc | I19: TT 232/2012/TT-BTC Điều 2 | J19: 5111 | 5311 | 5321 | K19: 3 | L19: 0.14285714
A20: 6 | B20: acord_business_purpose_cd | C20: character(3) | D20: ✓ | H20: Đối chiếu quốc tế ACORD: NBS / RWL / PCH / XLC | I20: ACORD P&C BusinessPurposeTypeCd | J20: NBS | PCH | RWL | K20: 4 | L20: 0
A21: 7 | B21: note | C21: character varying(300) | H21: Ghi chú | J21: Doanh thu phí bảo hiểm gốc | Giảm phí bảo hiểm gốc – khoản giảm thu ( | Hoàn phí bảo hiểm gốc – khoản giảm thu ( | K21: 7 | L21: 0
B24: Khóa ngoại — bảng này tham chiếu tới
B25: Cột | C25: → Bảng cha | D25: Cột cha | E25: Ý nghĩa
B26: (không có)
B28: Được tham chiếu bởi — bảng con trỏ tới bảng này
B29: Bảng con | C29: Cột | D29: → Cột của bảng này | E29: Ý nghĩa
B30: core.policy_transaction | C30: txn_type_code | D30: txn_type_code | E30: Loại giao dịch → ref.transaction_type
B32: Dữ liệu mẫu — 5 dòng đầu (sắp theo cột 'txn_type_code')
B33: txn_type_code | C33: txn_type_name | D33: premium_sign | E33: is_revenue_deduction | F33: gl_account | G33: acord_business_purpose_cd | H33: note
B34: CANCEL | C34: Hủy hợp đồng (hoàn phí thời gian còn lại) | D34: -1 | E34: TRUE | F34: 5311 | G34: XLC | H34: Hoàn phí do chấm dứt hợp đồng trước hạn
B35: END_DEC | C35: Sửa đổi bổ sung – giảm phí | D35: -1 | E35: TRUE | F35: 5321 | G35: PCH | H35: Giảm phí bảo hiểm gốc – khoản giảm thu (NĐ 46/2023 Đ49 k3)
B36: END_INC | C36: Sửa đổi bổ sung – tăng phí | D36: 1 | E36: FALSE | F36: 5111 | G36: PCH | H36: Tăng số tiền BH / mở rộng phạm vi
B37: END_NOCHG | C37: Sửa đổi bổ sung – không đổi phí | D37: 0 | E37: FALSE | G37: PCH | H37: Thay đổi thông tin, không phát sinh phí
B38: NEW | C38: Cấp mới | D38: 1 | E38: FALSE | F38: 5111 | G38: NBS | H38: Doanh thu phí bảo hiểm gốc

Sheet ref.insurer
A1: ref.insurer — Doanh nghiệp bảo hiểm tham gia đồng bảo hiểm (ẩn danh); OWN = chính công ty
A2: ← Về Tổng quan bảng
A4: Schema | B4: ref
A5: Bảng | B5: insurer
A6: Lớp | B6: Danh mục
A7: Mô tả | B7: Doanh nghiệp bảo hiểm tham gia đồng bảo hiểm (ẩn danh); OWN = chính công ty
A8: Grain (1 dòng là gì) | B8: 1 dòng / DNBH
A9: Khóa chính | B9: insurer_code
A10: Số cột | B10: =COUNT($A$15:$A$400)
A11: Số dòng (dummy) | B11: 7
A12: Căn cứ / chuẩn tham chiếu | B12: Luật KDBH 2022 Điều 4 khoản 29
A14: STT | B14: Cột | C14: Kiểu dữ liệu | D14: NOT NULL | E14: Khóa chính | F14: Khóa ngoại → | G14: UNIQUE | H14: Mô tả | I14: Căn cứ / nguồn | J14: Giá trị mẫu | K14: Số giá trị khác nhau | L14: % NULL
A15: 1 | B15: insurer_code | C15: character varying(10) | D15: ✓ | E15: PK | H15: Mã DNBH; 'OWN' = chính công ty | J15: CO_A | CO_B | CO_C | K15: 7 | L15: 0
A16: 2 | B16: insurer_name | C16: character varying(200) | D16: ✓ | H16: Tên DNBH (ẩn danh) | J16: Doanh nghiệp bảo hiểm phi nhân thọ A | Doanh nghiệp bảo hiểm phi nhân thọ B | Doanh nghiệp bảo hiểm phi nhân thọ C | K16: 7 | L16: 0
A17: 3 | B17: is_own_company | C17: boolean | D17: ✓ | H17: TRUE = chính công ty | J17: false | true | K17: 2 | L17: 0
B20: Khóa ngoại — bảng này tham chiếu tới
B21: Cột | C21: → Bảng cha | D21: Cột cha | E21: Ý nghĩa
B22: (không có)
B24: Được tham chiếu bởi — bảng con trỏ tới bảng này
B25: Bảng con | C25: Cột | D25: → Cột của bảng này | E25: Ý nghĩa
B26: core.coinsurance_share | C26: insurer_code | D26: insurer_code | E26: DNBH tham gia → ref.insurer ('OWN' = chính công ty)
B28: Dữ liệu mẫu — 5 dòng đầu (sắp theo cột 'insurer_code')
B29: insurer_code | C29: insurer_name | D29: is_own_company
B30: CO_A | C30: Doanh nghiệp bảo hiểm phi nhân thọ A | D30: FALSE
B31: CO_B | C31: Doanh nghiệp bảo hiểm phi nhân thọ B | D31: FALSE
B32: CO_C | C32: Doanh nghiệp bảo hiểm phi nhân thọ C | D32: FALSE
B33: CO_D | C33: Doanh nghiệp bảo hiểm phi nhân thọ D | D33: FALSE
B34: CO_E | C34: Doanh nghiệp bảo hiểm phi nhân thọ E | D34: FALSE

Sheet ref.allocation_type
A1: ref.allocation_type — Loại phân bổ doanh thu giữa các đơn vị
A2: ← Về Tổng quan bảng
A4: Schema | B4: ref
A5: Bảng | B5: allocation_type
A6: Lớp | B6: Danh mục
A7: Mô tả | B7: Loại phân bổ doanh thu giữa các đơn vị
A8: Grain (1 dòng là gì) | B8: 1 dòng / loại
A9: Khóa chính | B9: allocation_type_code
A10: Số cột | B10: =COUNT($A$15:$A$400)
A11: Số dòng (dummy) | B11: 3
A12: Căn cứ / chuẩn tham chiếu | B12: Thông lệ quản trị nội bộ
A14: STT | B14: Cột | C14: Kiểu dữ liệu | D14: NOT NULL | E14: Khóa chính | F14: Khóa ngoại → | G14: UNIQUE | H14: Mô tả | I14: Căn cứ / nguồn | J14: Giá trị mẫu | K14: Số giá trị khác nhau | L14: % NULL
A15: 1 | B15: allocation_type_code | C15: character varying(20) | D15: ✓ | E15: PK | H15: TU_KHAI_THAC / HO_TRO_CHEO / CHUYEN_GIAO | J15: CHUYEN_GIAO | HO_TRO_CHEO | TU_KHAI_THAC | K15: 3 | L15: 0
A16: 2 | B16: allocation_type_name | C16: character varying(150) | D16: ✓ | H16: Tên loại phân bổ | J16: Chuyển giao doanh thu | Hợp tác khai thác giữa các đơn vị | Tự khai thác | K16: 3 | L16: 0
A17: 3 | B17: note | C17: character varying(300) | H17: Diễn giải | J17: 100% doanh thu cho đơn vị cấp đơn | Chia doanh thu theo tỷ lệ đóng góp khai | Đơn vị cấp đơn chuyển doanh thu cho đơn | K17: 3 | L17: 0
B20: Khóa ngoại — bảng này tham chiếu tới
B21: Cột | C21: → Bảng cha | D21: Cột cha | E21: Ý nghĩa
B22: (không có)
B24: Được tham chiếu bởi — bảng con trỏ tới bảng này
B25: Bảng con | C25: Cột | D25: → Cột của bảng này | E25: Ý nghĩa
B26: core.revenue_allocation | C26: allocation_type_code | D26: allocation_type_code | E26: Loại phân bổ → ref.allocation_type
B28: Dữ liệu mẫu — 5 dòng đầu (sắp theo cột 'allocation_type_code')
B29: allocation_type_code | C29: allocation_type_name | D29: note
B30: CHUYEN_GIAO | C30: Chuyển giao doanh thu | D30: Đơn vị cấp đơn chuyển doanh thu cho đơn vị quản lý khách hàng/địa bàn
B31: HO_TRO_CHEO | C31: Hợp tác khai thác giữa các đơn vị | D31: Chia doanh thu theo tỷ lệ đóng góp khai thác
B32: TU_KHAI_THAC | C32: Tự khai thác | D32: 100% doanh thu cho đơn vị cấp đơn

Sheet core.policy
A1: core.policy — Hợp đồng / đơn bảo hiểm
A2: ← Về Tổng quan bảng
A4: Schema | B4: core
A5: Bảng | B5: policy
A6: Lớp | B6: Giao dịch
A7: Mô tả | B7: Hợp đồng / đơn bảo hiểm
A8: Grain (1 dòng là gì) | B8: 1 dòng / hợp đồng
A9: Khóa chính | B9: policy_id
A10: Số cột | B10: =COUNT($A$15:$A$400)
A11: Số dòng (dummy) | B11: 4082637
A12: Căn cứ / chuẩn tham chiếu | B12: Luật KDBH 2022; ACORD Policy; IBM IIW Agreement
A14: STT | B14: Cột | C14: Kiểu dữ liệu | D14: NOT NULL | E14: Khóa chính | F14: Khóa ngoại → | G14: UNIQUE | H14: Mô tả | I14: Căn cứ / nguồn | J14: Giá trị mẫu | K14: Số giá trị khác nhau | L14: % NULL
A15: 1 | B15: policy_id | C15: bigint | D15: ✓ | E15: PK | H15: Khóa hợp đồng | J15: 60000001 | 60000002 | 60000003 | K15: 4082637 | L15: 0
A16: 2 | B16: policy_no | C16: character varying(40) | D16: ✓ | G16: ✓ | H16: Số hợp đồng: <năm>-<đơn vị>-<nhóm SP>-<số thứ tự> | J16: 2026-AGI-BHN-2000001 | 2026-AGI-BHN-2000002 | 2026-AGI-BHN-2000003 | K16: 4082637 | L16: 0
A17: 3 | B17: issuing_company_code | C17: character varying(10) | D17: ✓ | F17: ref.company.company_code | H17: Đơn vị cấp đơn → ref.company | J17: AGI | ALC | BTB | K17: 48 | L17: 0
A18: 4 | B18: customer_code | C18: character varying(20) | D18: ✓ | F18: ref.customer.customer_code | H18: Bên mua bảo hiểm → ref.customer | J18: KH610000001 | KH610000002 | KH610000003 | K18: 1696375 | L18: 0
A19: 5 | B19: channel_code | C19: character varying(20) | F19: ref.channel.channel_code | H19: Kênh bán → ref.channel. Bắt buộc theo nghiệp vụ; NULL = nguồn không khai báo (~0,5%, dữ liệu bẩn có chủ đích) — lớp phân tích gán 'CHUA_XD' | I19: TT 67/2023/TT-BTC Mẫu 3-PNT (báo cáo theo kênh) | J19: BANCA | DAI_LY_CN | DAI_LY_TC | K19: 7 | L19: 0.0011446034
A20: 6 | B20: partner_code | C20: character varying(20) | F20: ref.partner.partner_code | H20: Đối tác phân phối → ref.partner. Không bắt buộc: NULL = không qua đối tác (bán trực tiếp, đại lý cá nhân, đấu thầu, website/app công ty) — hợp lệ; lớp phân tích gán 'WEB_APP' (kênh điện tử) / 'KHONG_QUA_DT' (kênh khác) | I20: Quy ước dự án 13/10/2026 | J20: ATADI | BC_A | CTTC_A | K20: 39 | L20: 0.12193614
A21: 7 | B21: currency_code | C21: character(3) | D21: ✓ | F21: ref.currency.currency_code | H21: Loại tiền của hợp đồng → ref.currency | J21: USD | VND | K21: 2 | L21: 0
A22: 8 | B22: issue_date | C22: date | D22: ✓ | H22: Ngày cấp đơn / giao kết hợp đồng | J22: 2026-08-01 | 2026-08-02 | 2026-08-03 | K22: 61 | L22: 0
A23: 9 | B23: effective_date | C23: date | D23: ✓ | H23: Ngày bắt đầu thời hạn bảo hiểm | J23: 2026-08-01 | 2026-08-02 | 2026-08-03 | K23: 778 | L23: 0
A24: 10 | B24: expiry_date | C24: date | D24: ✓ | H24: Ngày kết thúc thời hạn bảo hiểm | J24: 2026-08-01 | 2026-08-02 | 2026-08-03 | K24: 979 | L24: 0
A25: 11 | B25: is_group_policy | C25: boolean | D25: ✓ | H25: TRUE = đơn nhóm / đơn lô giấy chứng nhận | J25: false | true | K25: 2 | L25: 0
A26: 13 | B26: prev_policy_no | C26: character varying(40) | H26: Số hợp đồng năm trước được tái tục (hợp đồng ngoài kỳ dữ liệu nên lưu text; NULL = cấp mới) | J26: 2025-AGI-BHN-0264157 | 2025-AGI-BHN-0486076 | 2025-AGI-BHN-0661096 | K26: 172888 | L26: 0.95764723
A27: 14 | B27: renewal_of_policy_id | C27: bigint | F27: core.policy.policy_id | H27: Hợp đồng được tái tục → core.policy (NULL = đơn mới) | K27: 0 | L27: 1
B30: Khóa ngoại — bảng này tham chiếu tới
B31: Cột | C31: → Bảng cha | D31: Cột cha | E31: Ý nghĩa
B32: issuing_company_code | C32: ref.company | D32: company_code | E32: Đơn vị cấp đơn → ref.company
B33: customer_code | C33: ref.customer | D33: customer_code | E33: Bên mua bảo hiểm → ref.customer
B34: channel_code | C34: ref.channel | D34: channel_code | E34: Kênh bán → ref.channel. Bắt buộc theo nghiệp vụ; NULL = nguồn không khai báo (~0
B35: partner_code | C35: ref.partner | D35: partner_code | E35: Đối tác phân phối → ref.partner. Không bắt buộc: NULL = không qua đối tác (bán t
B36: currency_code | C36: ref.currency | D36: currency_code | E36: Loại tiền của hợp đồng → ref.currency
B37: renewal_of_policy_id | C37: core.policy | D37: policy_id | E37: Hợp đồng được tái tục → core.policy (NULL = đơn mới)
B39: Được tham chiếu bởi — bảng con trỏ tới bảng này
B40: Bảng con | C40: Cột | D40: → Cột của bảng này | E40: Ý nghĩa
B41: core.coinsurance_share | C41: policy_id | D41: policy_id | E41: Hợp đồng → core.policy
B42: core.policy | C42: renewal_of_policy_id | D42: policy_id | E42: Hợp đồng được tái tục → core.policy (NULL = đơn mới)
B43: core.policy_transaction | C43: policy_id | D43: policy_id | E43: Hợp đồng → core.policy
B44: core.revenue_allocation | C44: policy_id | D44: policy_id | E44: Hợp đồng → core.policy
B46: Dữ liệu mẫu — 5 dòng đầu (sắp theo cột 'policy_id')
B47: policy_id | C47: policy_no | D47: issuing_company_code | E47: customer_code | F47: channel_code | G47: partner_code | H47: currency_code | I47: issue_date | J47: effective_date | K47: expiry_date | L47: is_group_policy | M47: prev_policy_no | N47: renewal_of_policy_id
B48: 60000001 | C48: 2026-DGT-XSC-6000001 | D48: DGT | E48: KH670050988 | F48: DIEN_TU | G48: GREEN_SM | H48: VND | I48: 46235 | J48: 46235 | K48: 46235 | L48: FALSE
B49: 60000002 | C49: 2026-DGT-FDC-2000001 | D49: DGT | E49: KH670074759 | F49: DIEN_TU | G49: GREEN_SM | H49: VND | I49: 46235 | J49: 46235 | K49: 46235 | L49: FALSE
B50: 60000003 | C50: 2026-DGT-TBD-2000001 | D50: DGT | E50: KH670605908 | F50: DIEN_TU | G50: FUSE | H50: VND | I50: 46235 | J50: 46235 | K50: 46599 | L50: FALSE
B51: 60000004 | C51: 2026-DGT-FDC-2000002 | D51: DGT | E51: KH670129618 | F51: DIEN_TU | G51: GREEN_SM | H51: VND | I51: 46235 | J51: 46235 | K51: 46235 | L51: FALSE
B52: 60000005 | C52: 2026-DGT-FDC-2000003 | D52: DGT | E52: KH670349391 | F52: DIEN_TU | G52: GREEN_SM | H52: VND | I52: 46235 | J52: 46235 | K52: 46235 | L52: FALSE

Sheet core.policy_transaction
A1: core.policy_transaction — Giao dịch phát sinh phí của hợp đồng (cấp mới, tái tục, SĐBS, hoàn phí, hủy)
A2: ← Về Tổng quan bảng
A4: Schema | B4: core
A5: Bảng | B5: policy_transaction
A6: Lớp | B6: Giao dịch
A7: Mô tả | B7: Giao dịch phát sinh phí của hợp đồng (cấp mới, tái tục, SĐBS, hoàn phí, hủy)
A8: Grain (1 dòng là gì) | B8: 1 dòng / giao dịch
A9: Khóa chính | B9: txn_id
A10: Số cột | B10: =COUNT($A$15:$A$400)
A11: Số dòng (dummy) | B11: 4098401
A12: Căn cứ / chuẩn tham chiếu | B12: NĐ 46/2023/NĐ-CP Điều 49; TT 232/2012/TT-BTC TK 5111/5311/5321; Microsoft CDM PolicyTransaction
A14: STT | B14: Cột | C14: Kiểu dữ liệu | D14: NOT NULL | E14: Khóa chính | F14: Khóa ngoại → | G14: UNIQUE | H14: Mô tả | I14: Căn cứ / nguồn | J14: Giá trị mẫu | K14: Số giá trị khác nhau | L14: % NULL
A15: 1 | B15: txn_id | C15: bigint | D15: ✓ | E15: PK | H15: Khóa giao dịch | J15: 60000001 | 60000002 | 60000003 | K15: 4098401 | L15: 0
A16: 2 | B16: policy_id | C16: bigint | D16: ✓ | F16: core.policy.policy_id | H16: Hợp đồng → core.policy | J16: 60000001 | 60000002 | 60000003 | K16: 4082637 | L16: 0
A17: 3 | B17: txn_no | C17: character varying(50) | D17: ✓ | H17: Số chứng từ: <số hợp đồng>/<thứ tự giao dịch> | J17: 2026-AGI-BHN-2000001/00 | 2026-AGI-BHN-2000002/00 | 2026-AGI-BHN-2000003/00 | K17: 4098401 | L17: 0
A18: 4 | B18: txn_type_code | C18: character varying(20) | D18: ✓ | F18: ref.transaction_type.txn_type_code | H18: Loại giao dịch → ref.transaction_type | J18: CANCEL | END_DEC | END_INC | K18: 7 | L18: 0
A19: 5 | B19: txn_date | C19: date | D19: ✓ | H19: Ngày chứng từ (ngày phát sinh giao dịch) | J19: 2026-08-01 | 2026-08-02 | 2026-08-03 | K19: 61 | L19: 0
A20: 6 | B20: accounting_date | C20: date | D20: ✓ | H20: Ngày ghi nhận doanh thu = ngày phát sinh trách nhiệm bảo hiểm (cấp mới/tái tục: max(ngày cấp, ngày hiệu lực); SĐBS: ngày chứng từ) | I20: TT 67/2023/TT-BTC Điều 41 khoản 1 | J20: 2026-08-01 | 2026-08-02 | 2026-08-03 | K20: 778 | L20: 0
A21: 7 | B21: status | C21: character varying(10) | D21: ✓ | H21: Trạng thái: APPROVED (tính doanh thu) / PENDING / VOID | J21: APPROVED | PENDING | VOID | K21: 3 | L21: 0
A22: 8 | B22: fx_rate | C22: numeric(18,2) | D22: ✓ | H22: Tỷ giá hạch toán tại tháng ghi nhận (VND = 1) | I22: ref.fx_rate | J22: 1.00 | 26050.00 | 26150.00 | K22: 6 | L22: 0
A23: 9 | B23: created_by | C23: character varying(30) | D23: ✓ | H23: Người tạo chứng từ (giả) | J23: AGI.NV01 | AGI.NV02 | AGI.NV03 | K23: 1889 | L23: 0
A24: 10 | B24: created_at | C24: timestamp(0) without time zone | D24: ✓ | H24: Thời điểm tạo chứng từ | J24: 2026-08-01 00:00:04 | 2026-08-01 00:00:08 | 2026-08-01 00:00:09 | K24: 2538911 | L24: 0
B27: Khóa ngoại — bảng này tham chiếu tới
B28: Cột | C28: → Bảng cha | D28: Cột cha | E28: Ý nghĩa
B29: policy_id | C29: core.policy | D29: policy_id | E29: Hợp đồng → core.policy
B30: txn_type_code | C30: ref.transaction_type | D30: txn_type_code | E30: Loại giao dịch → ref.transaction_type
B32: Được tham chiếu bởi — bảng con trỏ tới bảng này
B33: Bảng con | C33: Cột | D33: → Cột của bảng này | E33: Ý nghĩa
B34: core.transaction_coverage | C34: txn_id | D34: txn_id | E34: Giao dịch → core.policy_transaction
B36: Dữ liệu mẫu — 5 dòng đầu (sắp theo cột 'txn_id')
B37: txn_id | C37: policy_id | D37: txn_no | E37: txn_type_code | F37: txn_date | G37: accounting_date | H37: status | I37: fx_rate | J37: created_by | K37: created_at
B38: 60000001 | C38: 60002844 | D38: 2026-DGT-XSC-6001806/00 | E38: NEW | F38: 46235 | G38: 46235 | H38: APPROVED | I38: 1 | J38: API.GREEN_SM | K38: 46235
B39: 60000002 | C39: 60028548 | D39: 2026-DGT-XSC-6018131/00 | E39: NEW | F39: 46235 | G39: 46235 | H39: APPROVED | I39: 1 | J39: API.GREEN_SM | K39: 46235
B40: 60000003 | C40: 60052317 | D40: 2026-DGT-XSC-6033233/00 | E40: NEW | F40: 46235 | G40: 46235 | H40: APPROVED | I40: 1 | J40: API.GREEN_SM | K40: 46235
B41: 60000004 | C41: 60060394 | D41: 2026-DGT-XSC-6038333/00 | E41: NEW | F41: 46235 | G41: 46235 | H41: APPROVED | I41: 1 | J41: API.GREEN_SM | K41: 46235
B42: 60000005 | C42: 60031997 | D42: 2026-DGT-XSC-6020284/00 | E42: NEW | F42: 46235 | G42: 46235 | H42: APPROVED | I42: 1 | J42: API.GREEN_SM | K42: 46235

Sheet core.transaction_coverage
A1: core.transaction_coverage — Phí 100% hợp đồng theo từng sản phẩm của giao dịch
A2: ← Về Tổng quan bảng
A4: Schema | B4: core
A5: Bảng | B5: transaction_coverage
A6: Lớp | B6: Giao dịch
A7: Mô tả | B7: Phí 100% hợp đồng theo từng sản phẩm của giao dịch
A8: Grain (1 dòng là gì) | B8: 1 dòng / giao dịch × sản phẩm
A9: Khóa chính | B9: coverage_id
A10: Số cột | B10: =COUNT($A$15:$A$400)
A11: Số dòng (dummy) | B11: 4127680
A12: Căn cứ / chuẩn tham chiếu | B12: TT 232/2012/TT-BTC Điều 12 (DT chi tiết theo nghiệp vụ); ACORD Coverage NetChangeAmt
A14: STT | B14: Cột | C14: Kiểu dữ liệu | D14: NOT NULL | E14: Khóa chính | F14: Khóa ngoại → | G14: UNIQUE | H14: Mô tả | I14: Căn cứ / nguồn | J14: Giá trị mẫu | K14: Số giá trị khác nhau | L14: % NULL
A15: 1 | B15: coverage_id | C15: bigint | D15: ✓ | E15: PK | H15: Khóa dòng phí | J15: 60000001 | 60000002 | 60000003 | K15: 4127680 | L15: 0
A16: 2 | B16: txn_id | C16: bigint | D16: ✓ | F16: core.policy_transaction.txn_id | H16: Giao dịch → core.policy_transaction | J16: 60000001 | 60000002 | 60000003 | K16: 4098401 | L16: 0
A17: 3 | B17: product_code | C17: character varying(20) | D17: ✓ | F17: ref.product.product_code | H17: Sản phẩm → ref.product | J17: CHN_BB | CHN_TN | MV_DELAYCARE | K17: 23 | L17: 0
A18: 4 | B18: sum_insured | C18: numeric(20,2) | D18: ✓ | H18: Số tiền bảo hiểm (nguyên tệ; tổng cho cả lô / nhóm) | J18: 0.00 | -10000.00 | 10000.00 | K18: 18381 | L18: 0
A19: 5 | B19: premium_rate_pct | C19: numeric(9,6) | H19: Tỷ lệ phí % (chỉ sản phẩm tính theo % STBH) | I19: NĐ 67/2023/NĐ-CP PL II (cháy nổ bắt buộc) | J19: 0.049978 | 0.050000 | 0.050001 | K19: 67009 | L19: 0.82207414
A20: 6 | B20: insured_count | C20: integer | D20: ✓ | H20: Số người / xe / giấy chứng nhận được bảo hiểm | J20: 0 | 1 | 10 | K20: 654 | L20: 0
A21: 7 | B21: premium_orig | C21: numeric(18,2) | D21: ✓ | H21: Phí 100% hợp đồng, nguyên tệ, chưa VAT; là phần THAY ĐỔI phí của giao dịch (âm với giảm/hoàn/hủy) | I21: ACORD Coverage NetChangeAmt | J21: 0.00 | 100.00 | 1000.00 | K21: 95396 | L21: 0
A22: 8 | B22: premium_vnd | C22: numeric(18,0) | D22: ✓ | H22: Phí quy đổi VND, bằng premium_orig × fx_rate | J22: 0 | 1000 | 10000 | K22: 95524 | L22: 0
A23: 9 | B23: vat_vnd | C23: numeric(18,0) | D23: ✓ | H23: Thuế GTGT (VND) = premium_vnd × vat_rate | I23: Luật GTGT 48/2024 | J23: 0 | 1000 | 10000 | K23: 52027 | L23: 0
A24: 10 | B24: commission_rate_pct | C24: numeric(7,4) | D24: ✓ | H24: Tỷ lệ hoa hồng % (0 với bán trực tiếp, đấu thầu); ≤ ref.product.max_commission_pct | I24: TT 67/2023/TT-BTC Điều 51 | J24: 0.0000 | 0.0067 | 0.0226 | K24: 176803 | L24: 0
B27: Khóa ngoại — bảng này tham chiếu tới
B28: Cột | C28: → Bảng cha | D28: Cột cha | E28: Ý nghĩa
B29: txn_id | C29: core.policy_transaction | D29: txn_id | E29: Giao dịch → core.policy_transaction
B30: product_code | C30: ref.product | D30: product_code | E30: Sản phẩm → ref.product
B32: Được tham chiếu bởi — bảng con trỏ tới bảng này
B33: Bảng con | C33: Cột | D33: → Cột của bảng này | E33: Ý nghĩa
B34: (không có)
B36: Dữ liệu mẫu — 5 dòng đầu (sắp theo cột 'coverage_id')
B37: coverage_id | C37: txn_id | D37: product_code | E37: sum_insured | F37: premium_rate_pct | G37: insured_count | H37: premium_orig | I37: premium_vnd | J37: vat_vnd | K37: commission_rate_pct
B38: 60000001 | C38: 60000001 | D38: MV_XSM_CARE | E38: 500000000 | G38: 1 | H38: 1000 | I38: 1000 | J38: 0 | K38: 9.5702
B39: 60000002 | C39: 60000002 | D39: MV_XSM_CARE | E39: 500000000 | G39: 1 | H39: 1000 | I39: 1000 | J39: 0 | K39: 10.8353
B40: 60000003 | C40: 60000003 | D40: MV_XSM_CARE | E40: 500000000 | G40: 1 | H40: 1000 | I40: 1000 | J40: 0 | K40: 11.2706
B41: 60000004 | C41: 60000004 | D41: MV_XSM_CARE | E41: 500000000 | G41: 1 | H41: 2000 | I41: 2000 | J41: 0 | K41: 8.7582
B42: 60000005 | C42: 60000005 | D42: MV_XSM_CARE | E42: 500000000 | G42: 1 | H42: 2000 | I42: 2000 | J42: 0 | K42: 13.3531

Sheet core.coinsurance_share
A1: core.coinsurance_share — Tỷ lệ tham gia đồng bảo hiểm của từng DNBH trên hợp đồng (tổng = 100%)
A2: ← Về Tổng quan bảng
A4: Schema | B4: core
A5: Bảng | B5: coinsurance_share
A6: Lớp | B6: Giao dịch
A7: Mô tả | B7: Tỷ lệ tham gia đồng bảo hiểm của từng DNBH trên hợp đồng (tổng = 100%)
A8: Grain (1 dòng là gì) | B8: 1 dòng / hợp đồng × DNBH
A9: Khóa chính | B9: insurer_code, policy_id
A10: Số cột | B10: =COUNT($A$15:$A$400)
A11: Số dòng (dummy) | B11: 4082967
A12: Căn cứ / chuẩn tham chiếu | B12: Luật KDBH 2022 Điều 4 k29; TT 232/2012/TT-BTC Điều 19; TT 67/2023/TT-BTC Điều 41 k2
A14: STT | B14: Cột | C14: Kiểu dữ liệu | D14: NOT NULL | E14: Khóa chính | F14: Khóa ngoại → | G14: UNIQUE | H14: Mô tả | I14: Căn cứ / nguồn | J14: Giá trị mẫu | K14: Số giá trị khác nhau | L14: % NULL
A15: 1 | B15: policy_id | C15: bigint | D15: ✓ | E15: PK | F15: core.policy.policy_id | H15: Hợp đồng → core.policy | J15: 60000001 | 60000002 | 60000003 | K15: 4082637 | L15: 0
A16: 2 | B16: insurer_code | C16: character varying(10) | D16: ✓ | E16: PK | F16: ref.insurer.insurer_code | H16: DNBH tham gia → ref.insurer ('OWN' = chính công ty) | J16: CO_A | CO_B | CO_C | K16: 7 | L16: 0
A17: 3 | B17: role | C17: character varying(10) | D17: ✓ | H17: Vai trò: LEADER (đồng chính) / FOLLOWER (đồng phụ) / SOLE (bảo hiểm 100%) | I17: TT 232/2012/TT-BTC Điều 19 | J17: FOLLOWER | LEADER | SOLE | K17: 3 | L17: 0
A18: 4 | B18: share_pct | C18: numeric(7,4) | D18: ✓ | H18: Tỷ lệ tham gia %; tổng theo hợp đồng = 100 | I18: Luật KDBH 2022 Điều 4 khoản 29 | J18: 10.0000 | 100.0000 | 10.0900 | K18: 290 | L18: 0
B21: Khóa ngoại — bảng này tham chiếu tới
B22: Cột | C22: → Bảng cha | D22: Cột cha | E22: Ý nghĩa
B23: policy_id | C23: core.policy | D23: policy_id | E23: Hợp đồng → core.policy
B24: insurer_code | C24: ref.insurer | D24: insurer_code | E24: DNBH tham gia → ref.insurer ('OWN' = chính công ty)
B26: Được tham chiếu bởi — bảng con trỏ tới bảng này
B27: Bảng con | C27: Cột | D27: → Cột của bảng này | E27: Ý nghĩa
B28: (không có)
B30: Dữ liệu mẫu — 5 dòng đầu (sắp theo cột 'policy_id')
B31: policy_id | C31: insurer_code | D31: role | E31: share_pct
B32: 60000001 | C32: OWN | D32: SOLE | E32: 100
B33: 60000002 | C33: OWN | D33: SOLE | E33: 100
B34: 60000003 | C34: OWN | D34: SOLE | E34: 100
B35: 60000004 | C35: OWN | D35: SOLE | E35: 100
B36: 60000005 | C36: OWN | D36: SOLE | E36: 100

Sheet core.revenue_allocation
A1: core.revenue_allocation — Phân bổ doanh thu phần của công ty cho các đơn vị (tổng = 100%)
A2: ← Về Tổng quan bảng
A4: Schema | B4: core
A5: Bảng | B5: revenue_allocation
A6: Lớp | B6: Giao dịch
A7: Mô tả | B7: Phân bổ doanh thu phần của công ty cho các đơn vị (tổng = 100%)
A8: Grain (1 dòng là gì) | B8: 1 dòng / hợp đồng × đơn vị
A9: Khóa chính | B9: company_code, policy_id
A10: Số cột | B10: =COUNT($A$15:$A$400)
A11: Số dòng (dummy) | B11: 4152252
A12: Căn cứ / chuẩn tham chiếu | B12: Thông lệ quản trị Tổng công ty – công ty thành viên
A14: STT | B14: Cột | C14: Kiểu dữ liệu | D14: NOT NULL | E14: Khóa chính | F14: Khóa ngoại → | G14: UNIQUE | H14: Mô tả | I14: Căn cứ / nguồn | J14: Giá trị mẫu | K14: Số giá trị khác nhau | L14: % NULL
A15: 1 | B15: policy_id | C15: bigint | D15: ✓ | E15: PK | F15: core.policy.policy_id | H15: Hợp đồng → core.policy | J15: 60000001 | 60000002 | 60000003 | K15: 4082637 | L15: 0
A16: 2 | B16: company_code | C16: character varying(10) | D16: ✓ | E16: PK | F16: ref.company.company_code | H16: Đơn vị được phân bổ doanh thu → ref.company | J16: AGI | ALC | BTB | K16: 48 | L16: 0
A17: 3 | B17: allocation_type_code | C17: character varying(20) | D17: ✓ | F17: ref.allocation_type.allocation_type_code | H17: Loại phân bổ → ref.allocation_type | J17: CHUYEN_GIAO | HO_TRO_CHEO | TU_KHAI_THAC | K17: 3 | L17: 0
A18: 4 | B18: allocation_pct | C18: numeric(7,4) | D18: ✓ | H18: Tỷ lệ phân bổ %; tổng theo hợp đồng = 100 | J18: 100.0000 | 20.0000 | 30.0000 | K18: 8 | L18: 0
B21: Khóa ngoại — bảng này tham chiếu tới
B22: Cột | C22: → Bảng cha | D22: Cột cha | E22: Ý nghĩa
B23: policy_id | C23: core.policy | D23: policy_id | E23: Hợp đồng → core.policy
B24: company_code | C24: ref.company | D24: company_code | E24: Đơn vị được phân bổ doanh thu → ref.company
B25: allocation_type_code | C25: ref.allocation_type | D25: allocation_type_code | E25: Loại phân bổ → ref.allocation_type
B27: Được tham chiếu bởi — bảng con trỏ tới bảng này
B28: Bảng con | C28: Cột | D28: → Cột của bảng này | E28: Ý nghĩa
B29: (không có)
B31: Dữ liệu mẫu — 5 dòng đầu (sắp theo cột 'policy_id')
B32: policy_id | C32: company_code | D32: allocation_type_code | E32: allocation_pct
B33: 60000001 | C33: DGT | D33: TU_KHAI_THAC | E33: 100
B34: 60000002 | C34: DGT | D34: TU_KHAI_THAC | E34: 100
B35: 60000003 | C35: DGT | D35: TU_KHAI_THAC | E35: 100
B36: 60000004 | C36: DGT | D36: TU_KHAI_THAC | E36: 100
B37: 60000005 | C37: DGT | D37: TU_KHAI_THAC | E37: 100

Sheet DM Sản phẩm
A1: DM Sản phẩm
A2: Sinh tự động từ catalog PostgreSQL reportapi — bronze.ins_* (scripts/build_docs.py, DOCS_TARGET=volume) ngày 19/10/2026. Tên bảng ghi theo mô hình logic: ref.X / core.X = bronze.ins_X.
A4: product_code | B4: product_name | C4: product_group_name | D4: lob_name | E4: poc_group_name | F4: report_line_code | G4: is_compulsory | H4: pricing_basis | I4: vat_rate | J4: max_commission_pct | K4: solvency2_lob | L4: legal_basis
A5: XE_TNDS_MOTO | B5: Bảo hiểm bắt buộc trách nhiệm dân sự của chủ xe mô tô, xe gắn máy | C5: BH bắt buộc TNDS chủ xe | D5: Bảo hiểm xe cơ giới | E5: Xe cơ giới | F5: B.4a.1 | G5: TRUE | H5: TARIFF | I5: 10 | J5: 20 | K5: 4 Motor vehicle liability insurance | L5: NĐ 67/2023/NĐ-CP Phụ lục I (biểu phí TNDS bắt buộc)
A6: XE_TNDS_OTO | B6: Bảo hiểm bắt buộc trách nhiệm dân sự của chủ xe ô tô | C6: BH bắt buộc TNDS chủ xe | D6: Bảo hiểm xe cơ giới | E6: Xe cơ giới | F6: B.4a.2 | G6: TRUE | H6: TARIFF | I6: 10 | J6: 5 | K6: 4 Motor vehicle liability insurance | L6: NĐ 67/2023/NĐ-CP Phụ lục I (biểu phí TNDS bắt buộc)
A7: XE_VCX_MOTO | B7: Bảo hiểm vật chất xe mô tô, xe máy | C7: BH vật chất xe | D7: Bảo hiểm xe cơ giới | E7: Xe cơ giới | F7: B.4b | G7: FALSE | H7: RATE_ON_SI | I7: 10 | J7: 10 | K7: 5 Other motor insurance
A8: XE_VCX_OTO | B8: Bảo hiểm vật chất xe ô tô | C8: BH vật chất xe | D8: Bảo hiểm xe cơ giới | E8: Xe cơ giới | F8: B.4b | G8: FALSE | H8: RATE_ON_SI | I8: 10 | J8: 10 | K8: 5 Other motor insurance
A9: NG_HSSV_SK | B9: Bảo hiểm sức khỏe toàn diện học sinh, sinh viên | C9: BH học sinh – sinh viên | D9: Bảo hiểm sức khỏe | E9: Con người | F9: A.2 | G9: FALSE | H9: PER_PERSON | I9: 0 | J9: 20 | K9: 1 Medical expense insurance | L9: Không chịu thuế GTGT – Luật Thuế GTGT 48/2024/QH15 Điều 5 k8
A10: NG_HSSV_TN | B10: Bảo hiểm tai nạn học sinh, sinh viên | C10: BH học sinh – sinh viên | D10: Bảo hiểm sức khỏe | E10: Con người | F10: A.1 | G10: FALSE | H10: PER_PERSON | I10: 0 | J10: 20 | K10: 2 Income protection insurance (*) | L10: Không chịu thuế GTGT – Luật Thuế GTGT 48/2024/QH15 Điều 5 k8
A11: MV_DELAYCARE | B11: Bảo hiểm trễ chuyến bay (DelayCare) | C11: BH du lịch | D11: Bảo hiểm sức khỏe | E11: Con người | F11: A.2 | G11: FALSE | H11: PER_PERSON | I11: 0 | J11: 20 | K11: 12 Miscellaneous financial loss (*) | L11: Không chịu thuế GTGT – Luật Thuế GTGT 48/2024/QH15 Điều 5 k8
A12: NG_DL_ND | B12: Bảo hiểm du lịch trong nước | C12: BH du lịch | D12: Bảo hiểm sức khỏe | E12: Con người | F12: A.2 | G12: FALSE | H12: PER_PERSON | I12: 0 | J12: 20 | K12: 1 Medical expense insurance (*) | L12: Không chịu thuế GTGT – Luật Thuế GTGT 48/2024/QH15 Điều 5 k8
A13: NG_DL_QT | B13: Bảo hiểm du lịch quốc tế | C13: BH du lịch | D13: Bảo hiểm sức khỏe | E13: Con người | F13: A.2 | G13: FALSE | H13: PER_PERSON | I13: 0 | J13: 20 | K13: 1 Medical expense insurance (*) | L13: Không chịu thuế GTGT – Luật Thuế GTGT 48/2024/QH15 Điều 5 k8
A14: MV_FOOD_CARE | B14: Bảo hiểm đơn giao đồ ăn (Food Care) | C14: BH sinh mạng – tai nạn | D14: Bảo hiểm sức khỏe | E14: Con người | F14: A.1 | G14: FALSE | H14: PER_PERSON | I14: 0 | J14: 20 | K14: 2 Income protection insurance (*) | L14: Không chịu thuế GTGT – Luật Thuế GTGT 48/2024/QH15 Điều 5 k8
A15: MV_XSM_CARE | B15: Bảo hiểm tai nạn hành khách theo chuyến xe công nghệ (Green SM Care) | C15: BH sinh mạng – tai nạn | D15: Bảo hiểm sức khỏe | E15: Con người | F15: A.1 | G15: FALSE | H15: PER_PERSON | I15: 0 | J15: 20 | K15: 2 Income protection insurance (*) | L15: Không chịu thuế GTGT – Luật Thuế GTGT 48/2024/QH15 Điều 5 k8
A16: NG_NVV | B16: Bảo hiểm người vay vốn | C16: BH sinh mạng – tai nạn | D16: Bảo hiểm sức khỏe | E16: Con người | F16: A.1 | G16: FALSE | H16: RATE_ON_SI | I16: 0 | J16: 20 | K16: 2 Income protection insurance (*) | L16: Không chịu thuế GTGT – Luật Thuế GTGT 48/2024/QH15 Điều 5 k8
A17: NG_SM_CN | B17: Bảo hiểm sinh mạng cá nhân | C17: BH sinh mạng – tai nạn | D17: Bảo hiểm sức khỏe | E17: Con người | F17: A.1 | G17: FALSE | H17: RATE_ON_SI | I17: 0 | J17: 20 | K17: 2 Income protection insurance (*) | L17: Không chịu thuế GTGT – Luật Thuế GTGT 48/2024/QH15 Điều 5 k8
A18: NG_TN24 | B18: Bảo hiểm tai nạn con người 24/24 | C18: BH sinh mạng – tai nạn | D18: Bảo hiểm sức khỏe | E18: Con người | F18: A.1 | G18: FALSE | H18: RATE_ON_SI | I18: 0 | J18: 20 | K18: 2 Income protection insurance (*) | L18: Không chịu thuế GTGT – Luật Thuế GTGT 48/2024/QH15 Điều 5 k8
A19: NG_SK_BHN | B19: Bảo hiểm bệnh hiểm nghèo – ung thư | C19: BH sức khỏe | D19: Bảo hiểm sức khỏe | E19: Con người | F19: A.1 | G19: FALSE | H19: PER_PERSON | I19: 0 | J19: 20 | K19: 2 Income protection insurance (*) | L19: Không chịu thuế GTGT – Luật Thuế GTGT 48/2024/QH15 Điều 5 k8
A20: NG_SK_CN | B20: Bảo hiểm sức khỏe cá nhân | C20: BH sức khỏe | D20: Bảo hiểm sức khỏe | E20: Con người | F20: A.2 | G20: FALSE | H20: PER_PERSON | I20: 0 | J20: 20 | K20: 1 Medical expense insurance | L20: Không chịu thuế GTGT – Luật Thuế GTGT 48/2024/QH15 Điều 5 k8
A21: NG_SK_NHOM | B21: Bảo hiểm sức khỏe nhóm doanh nghiệp | C21: BH sức khỏe | D21: Bảo hiểm sức khỏe | E21: Con người | F21: A.2 | G21: FALSE | H21: PER_PERSON | I21: 0 | J21: 20 | K21: 1 Medical expense insurance | L21: Không chịu thuế GTGT – Luật Thuế GTGT 48/2024/QH15 Điều 5 k8
A22: MV_TBDT_TMDT | B22: Bảo hiểm thiết bị điện tử mua trên sàn TMĐT | C22: BH tài sản | D22: Bảo hiểm tài sản | E22: Tài sản | F22: B.1b | G22: FALSE | H22: RATE_ON_SI | I22: 10 | J22: 5 | K22: 7 Fire and other damage to property insurance (*)
A23: TS_MRR | B23: Bảo hiểm mọi rủi ro tài sản | C23: BH tài sản | D23: Bảo hiểm tài sản | E23: Tài sản | F23: B.1b | G23: FALSE | H23: RATE_ON_SI | I23: 10 | J23: 5 | K23: 7 Fire and other damage to property insurance
A24: TS_MRRCN | B24: Bảo hiểm mọi rủi ro công nghiệp | C24: BH tài sản | D24: Bảo hiểm tài sản | E24: Tài sản | F24: B.1b | G24: FALSE | H24: RATE_ON_SI | I24: 10 | J24: 5 | K24: 7 Fire and other damage to property insurance
A25: TS_NHA | B25: Bảo hiểm nhà tư nhân | C25: BH tài sản | D25: Bảo hiểm tài sản | E25: Tài sản | F25: B.1b | G25: FALSE | H25: RATE_ON_SI | I25: 10 | J25: 5 | K25: 7 Fire and other damage to property insurance
A26: CHN_BB | B26: Bảo hiểm cháy, nổ bắt buộc | C26: BH cháy nổ | D26: Bảo hiểm cháy, nổ | E26: Tài sản | F26: B.5a | G26: TRUE | H26: RATE_ON_SI | I26: 10 | J26: 5 | K26: 7 Fire and other damage to property insurance | L26: NĐ 67/2023/NĐ-CP Phụ lục II; thay thế bởi NĐ 105/2025/NĐ-CP Phụ lục VI từ 01/7/2
A27: CHN_TN | B27: Bảo hiểm cháy và các rủi ro đặc biệt (tự nguyện) | C27: BH cháy nổ | D27: Bảo hiểm cháy, nổ | E27: Tài sản | F27: B.5b | G27: FALSE | H27: RATE_ON_SI | I27: 10 | J27: 10 | K27: 7 Fire and other damage to property insurance

Sheet DM Kênh - Đối tác
A1: DM Kênh - Đối tác
A2: Sinh tự động từ catalog PostgreSQL reportapi — bronze.ins_* (scripts/build_docs.py, DOCS_TARGET=volume) ngày 19/10/2026. Tên bảng ghi theo mô hình logic: ref.X / core.X = bronze.ins_X.
A4: channel_code | B4: channel_name | C4: report_channel_group | D4: partner_code | E4: partner_name | F4: partner_type | G4: legal_basis
A5: TRUC_TIEP | B5: Bán trực tiếp | C5: Qua kênh phân phối khác | G5: Luật KDBH 2022 (08/2022/QH15) Điều 87 k4 điểm a
A6: DAI_LY_CN | B6: Đại lý cá nhân | C6: Qua kênh phân phối khác | G6: Luật KDBH 2022 (08/2022/QH15) Điều 87 k4 điểm b; Điều 124
A7: DAI_LY_TC | B7: Đại lý tổ chức | C7: Qua kênh phân phối khác | D7: BC_A | E7: Mạng lưới bưu cục A | F7: BUU_CHINH | G7: Luật KDBH 2022 (08/2022/QH15) Điều 87 k4 điểm b; Điều 124
A8: DAI_LY_TC | B8: Đại lý tổ chức | C8: Qua kênh phân phối khác | D8: DK_A | E8: Trung tâm đăng kiểm A | F8: DANG_KIEM | G8: Luật KDBH 2022 (08/2022/QH15) Điều 87 k4 điểm b; Điều 124
A9: DAI_LY_TC | B9: Đại lý tổ chức | C9: Qua kênh phân phối khác | D9: DK_B | E9: Trung tâm đăng kiểm B | F9: DANG_KIEM | G9: Luật KDBH 2022 (08/2022/QH15) Điều 87 k4 điểm b; Điều 124
A10: DAI_LY_TC | B10: Đại lý tổ chức | C10: Qua kênh phân phối khác | D10: DK_C | E10: Trung tâm đăng kiểm C | F10: DANG_KIEM | G10: Luật KDBH 2022 (08/2022/QH15) Điều 87 k4 điểm b; Điều 124
A11: DAI_LY_TC | B11: Đại lý tổ chức | C11: Qua kênh phân phối khác | D11: DK_D | E11: Trung tâm đăng kiểm D | F11: DANG_KIEM | G11: Luật KDBH 2022 (08/2022/QH15) Điều 87 k4 điểm b; Điều 124
A12: DAI_LY_TC | B12: Đại lý tổ chức | C12: Qua kênh phân phối khác | D12: GA_A | E12: Garage ô tô A | F12: GARAGE | G12: Luật KDBH 2022 (08/2022/QH15) Điều 87 k4 điểm b; Điều 124
A13: DAI_LY_TC | B13: Đại lý tổ chức | C13: Qua kênh phân phối khác | D13: GA_B | E13: Garage ô tô B | F13: GARAGE | G13: Luật KDBH 2022 (08/2022/QH15) Điều 87 k4 điểm b; Điều 124
A14: DAI_LY_TC | B14: Đại lý tổ chức | C14: Qua kênh phân phối khác | D14: LH_A | E14: Công ty lữ hành A | F14: CTY_LU_HANH | G14: Luật KDBH 2022 (08/2022/QH15) Điều 87 k4 điểm b; Điều 124
A15: DAI_LY_TC | B15: Đại lý tổ chức | C15: Qua kênh phân phối khác | D15: LH_B | E15: Công ty lữ hành B | F15: CTY_LU_HANH | G15: Luật KDBH 2022 (08/2022/QH15) Điều 87 k4 điểm b; Điều 124
A16: DAI_LY_TC | B16: Đại lý tổ chức | C16: Qua kênh phân phối khác | D16: LH_C | E16: Công ty lữ hành C | F16: CTY_LU_HANH | G16: Luật KDBH 2022 (08/2022/QH15) Điều 87 k4 điểm b; Điều 124
A17: DAI_LY_TC | B17: Đại lý tổ chức | C17: Qua kênh phân phối khác | D17: OTA_A | E17: Đại lý du lịch trực tuyến A | F17: OTA_DU_LICH | G17: Luật KDBH 2022 (08/2022/QH15) Điều 87 k4 điểm b; Điều 124
A18: DAI_LY_TC | B18: Đại lý tổ chức | C18: Qua kênh phân phối khác | D18: OTA_B | E18: Đại lý du lịch trực tuyến B | F18: OTA_DU_LICH | G18: Luật KDBH 2022 (08/2022/QH15) Điều 87 k4 điểm b; Điều 124
... A37: MOI_GIOI | B37: Môi giới bảo hiểm | C37: Qua kênh phân phối khác | D37: MG_D | E37: Công ty môi giới bảo hiểm D | F37: CTY_MOI_GIOI | G37: Luật KDBH 2022 (08/2022/QH15) Điều 87 k4 điểm b
A38: DAU_THAU | B38: Đấu thầu | C38: Qua kênh phân phối khác | G38: Luật KDBH 2022 (08/2022/QH15) Điều 87 k4 điểm c
A39: DIEN_TU | B39: Giao dịch điện tử (website/app, nền tảng đối tác) | C39: Qua môi trường mạng | D39: ATADI | E39: ATADI.vn – đại lý vé máy bay trực tuyến | F39: OTA_VE_MAY_BAY | G39: Luật KDBH 2022 (08/2022/QH15) Điều 87 k4 điểm d; TT 67/2023/TT-BTC Điều 4–5
A40: DIEN_TU | B40: Giao dịch điện tử (website/app, nền tảng đối tác) | C40: Qua môi trường mạng | D40: FUSE | E40: Fuse – nền tảng phân phối bảo hiểm trên Shopee, Lazada | F40: INSURTECH | G40: Luật KDBH 2022 (08/2022/QH15) Điều 87 k4 điểm d; TT 67/2023/TT-BTC Điều 4–5
A41: DIEN_TU | B41: Giao dịch điện tử (website/app, nền tảng đối tác) | C41: Qua môi trường mạng | D41: GREEN_SM | E41: Green SM (Xanh SM) – nền tảng gọi xe, giao đồ ăn | F41: NEN_TANG_DI_CHUYEN | G41: Luật KDBH 2022 (08/2022/QH15) Điều 87 k4 điểm d; TT 67/2023/TT-BTC Điều 4–5
A42: DIEN_TU | B42: Giao dịch điện tử (website/app, nền tảng đối tác) | C42: Qua môi trường mạng | D42: HK_A | E42: Hãng hàng không A | F42: HANG_HANG_KHONG | G42: Luật KDBH 2022 (08/2022/QH15) Điều 87 k4 điểm d; TT 67/2023/TT-BTC Điều 4–5
A43: DIEN_TU | B43: Giao dịch điện tử (website/app, nền tảng đối tác) | C43: Qua môi trường mạng | D43: TMDT_A | E43: Sàn thương mại điện tử A | F43: SAN_TMDT | G43: Luật KDBH 2022 (08/2022/QH15) Điều 87 k4 điểm d; TT 67/2023/TT-BTC Điều 4–5
A44: DIEN_TU | B44: Giao dịch điện tử (website/app, nền tảng đối tác) | C44: Qua môi trường mạng | D44: VI_A | E44: Ví điện tử A | F44: VI_DIEN_TU | G44: Luật KDBH 2022 (08/2022/QH15) Điều 87 k4 điểm d; TT 67/2023/TT-BTC Điều 4–5
A45: DIEN_TU | B45: Giao dịch điện tử (website/app, nền tảng đối tác) | C45: Qua môi trường mạng | D45: VI_B | E45: Ví điện tử B | F45: VI_DIEN_TU | G45: Luật KDBH 2022 (08/2022/QH15) Điều 87 k4 điểm d; TT 67/2023/TT-BTC Điều 4–5
A46: DIEN_TU | B46: Giao dịch điện tử (website/app, nền tảng đối tác) | C46: Qua môi trường mạng | D46: VT_A | E46: Nhà mạng viễn thông A | F46: VIEN_THONG | G46: Luật KDBH 2022 (08/2022/QH15) Điều 87 k4 điểm d; TT 67/2023/TT-BTC Điều 4–5

Sheet DM Loại giao dịch
A1: DM Loại giao dịch
A2: Sinh tự động từ catalog PostgreSQL reportapi — bronze.ins_* (scripts/build_docs.py, DOCS_TARGET=volume) ngày 19/10/2026. Tên bảng ghi theo mô hình logic: ref.X / core.X = bronze.ins_X.
A4: txn_type_code | B4: txn_type_name | C4: premium_sign | D4: is_revenue_deduction | E4: gl_account | F4: acord_business_purpose_cd | G4: note
A5: END_INC | B5: Sửa đổi bổ sung – tăng phí | C5: 1 | D5: FALSE | E5: 5111 | F5: PCH | G5: Tăng số tiền BH / mở rộng phạm vi
A6: NEW | B6: Cấp mới | C6: 1 | D6: FALSE | E6: 5111 | F6: NBS | G6: Doanh thu phí bảo hiểm gốc
A7: RENEW | B7: Tái tục | C7: 1 | D7: FALSE | E7: 5111 | F7: RWL | G7: Hợp đồng nối tiếp hợp đồng hết hạn
A8: END_NOCHG | B8: Sửa đổi bổ sung – không đổi phí | C8: 0 | D8: FALSE | F8: PCH | G8: Thay đổi thông tin, không phát sinh phí
A9: CANCEL | B9: Hủy hợp đồng (hoàn phí thời gian còn lại) | C9: -1 | D9: TRUE | E9: 5311 | F9: XLC | G9: Hoàn phí do chấm dứt hợp đồng trước hạn
A10: END_DEC | B10: Sửa đổi bổ sung – giảm phí | C10: -1 | D10: TRUE | E10: 5321 | F10: PCH | G10: Giảm phí bảo hiểm gốc – khoản giảm thu (NĐ 46/2023 Đ49 k3)
A11: REFUND | B11: Hoàn phí | C11: -1 | D11: TRUE | E11: 5311 | F11: PCH | G11: Hoàn phí bảo hiểm gốc – khoản giảm thu (NĐ 46/2023 Đ49 k3)

Sheet DM Đơn vị
A1: DM Đơn vị
A2: Sinh tự động từ catalog PostgreSQL reportapi — bronze.ins_* (scripts/build_docs.py, DOCS_TARGET=volume) ngày 19/10/2026. Tên bảng ghi theo mô hình logic: ref.X / core.X = bronze.ins_X.
A4: company_code | B4: company_name | C4: company_type | D4: parent_company_code | E4: province_name | F4: region_name
A5: PVI | B5: Tổng Công ty Bảo hiểm PVI | C5: CORPORATION | E5: Thành phố Hà Nội | F5: Miền Bắc
A6: DGT | B6: Bảo hiểm PVI Digital | C6: DIGITAL | D6: PVI | E6: Thành phố Hồ Chí Minh | F6: Miền Nam
A7: HO | B7: Trụ sở chính Tổng Công ty Bảo hiểm PVI – các Ban kinh doanh | C7: HEAD_OFFICE | D7: PVI | E7: Thành phố Hà Nội | F7: Miền Bắc
A8: AGI | B8: Bảo hiểm PVI An Giang | C8: MEMBER | D8: PVI | E8: Tỉnh An Giang | F8: Miền Nam
A9: ALC | B9: Bảo hiểm PVI Âu Lạc | C9: MEMBER | D9: PVI | E9: Thành phố Hà Nội | F9: Miền Bắc
A10: BTB | B10: Bảo hiểm PVI Bắc Trung Bộ | C10: MEMBER | D10: PVI | E10: Tỉnh Nghệ An | F10: Miền Trung
A11: BTH | B11: Bảo hiểm PVI Bến Thành | C11: MEMBER | D11: PVI | E11: Thành phố Hồ Chí Minh | F11: Miền Nam
A12: CLG | B12: Bảo hiểm PVI Cửu Long | C12: MEMBER | D12: PVI | E12: Tỉnh Vĩnh Long | F12: Miền Nam
A13: CMA | B13: Bảo hiểm PVI Cà Mau | C13: MEMBER | D13: PVI | E13: Tỉnh Cà Mau | F13: Miền Nam
A14: DDO | B14: Bảo hiểm PVI Đông Đô | C14: MEMBER | D14: PVI | E14: Thành phố Hà Nội | F14: Miền Bắc
A15: DHI | B15: Bảo hiểm PVI Duyên Hải | C15: MEMBER | D15: PVI | E15: Thành phố Hải Phòng | F15: Miền Bắc
A16: DKH | B16: Bảo hiểm PVI Đồng Khởi | C16: MEMBER | D16: PVI | E16: Thành phố Hồ Chí Minh | F16: Miền Nam
A17: DNA | B17: Bảo hiểm PVI Đà Nẵng | C17: MEMBER | D17: PVI | E17: Thành phố Đà Nẵng | F17: Miền Trung
... A53: VTU | B53: Bảo hiểm PVI Vũng Tàu | C53: MEMBER | D53: PVI | E53: Thành phố Hồ Chí Minh | F53: Miền Nam

Sheet DM Dòng báo cáo
A1: DM Dòng báo cáo
A2: Sinh tự động từ catalog PostgreSQL reportapi — bronze.ins_* (scripts/build_docs.py, DOCS_TARGET=volume) ngày 19/10/2026. Tên bảng ghi theo mô hình logic: ref.X / core.X = bronze.ins_X.
A4: report_line_code | B4: report_line_name | C4: parent_line_code | D4: legal_basis
A5: A | B5: Bảo hiểm sức khỏe | D5: TT 67/2023/TT-BTC Phụ lục VI – Mẫu 1-PNT/2-PNT
A6: A.1 | B6: Bảo hiểm sức khỏe, thân thể | C6: A | D6: TT 67/2023/TT-BTC Phụ lục VI – Mẫu 1-PNT/2-PNT
A7: A.2 | B7: Bảo hiểm chi phí y tế | C7: A | D7: TT 67/2023/TT-BTC Phụ lục VI – Mẫu 1-PNT/2-PNT
A8: B | B8: Bảo hiểm phi nhân thọ | D8: TT 67/2023/TT-BTC Phụ lục VI – Mẫu 1-PNT/2-PNT
A9: B.1 | B9: Bảo hiểm tài sản | C9: B | D9: TT 67/2023/TT-BTC Phụ lục VI – Mẫu 1-PNT/2-PNT
A10: B.1b | B10: Bảo hiểm tài sản khác | C10: B.1 | D10: TT 67/2023/TT-BTC Phụ lục VI – Mẫu 1-PNT/2-PNT
A11: B.4 | B11: Bảo hiểm xe cơ giới | C11: B | D11: TT 67/2023/TT-BTC Phụ lục VI – Mẫu 1-PNT/2-PNT
A12: B.4a | B12: Bảo hiểm bắt buộc TNDS của chủ xe cơ giới | C12: B.4 | D12: TT 67/2023/TT-BTC Phụ lục VI – Mẫu 1-PNT/2-PNT
A13: B.4a.1 | B13: TNDS bắt buộc – mô tô, xe gắn máy | C13: B.4a | D13: TT 67/2023/TT-BTC Phụ lục VI – Mẫu 1-PNT/2-PNT
A14: B.4a.2 | B14: TNDS bắt buộc – ô tô | C14: B.4a | D14: TT 67/2023/TT-BTC Phụ lục VI – Mẫu 1-PNT/2-PNT
A15: B.4b | B15: Bảo hiểm vật chất xe cơ giới | C15: B.4 | D15: TT 67/2023/TT-BTC Phụ lục VI – Mẫu 1-PNT/2-PNT
A16: B.5 | B16: Bảo hiểm cháy, nổ | C16: B | D16: TT 67/2023/TT-BTC Phụ lục VI – Mẫu 1-PNT/2-PNT
A17: B.5a | B17: Bảo hiểm cháy, nổ bắt buộc | C17: B.5 | D17: TT 67/2023/TT-BTC Phụ lục VI – Mẫu 1-PNT/2-PNT
A18: B.5b | B18: Bảo hiểm cháy, nổ khác | C18: B.5 | D18: TT 67/2023/TT-BTC Phụ lục VI – Mẫu 1-PNT/2-PNT
